{
  "annour-ivry-sur-seine": {
    "latitude": 48.8174572,
    "longitude": 2.3940178,
    "name": "Mosquée ANNOUR - Ivry-Sur-Seine",
    "url": "https://mawaqit.net/fr/annour-ivry-sur-seine",
    "label": "Mosquée ANNOUR - Ivry-Sur-Seine",
    "logo": null,
    "site": null,
    "association": "Association des musulmans d'ivry A M I",
    "steamUrl": "",
    "scrapedAt": "2025-09-05T11:21:16.493573+02:00",
    "parking": true,
    "ablutions": true,
    "ramadanMeal": true,
    "otherInfo": null,
    "womenSpace": true,
    "janazaPrayer": true,
    "aidPrayer": true,
    "adultCourses": true,
    "childrenCourses": true,
    "handicapAccessibility": true,
    "paymentWebsite": "https://www.helloasso.com/associations/collectif-annour/collectes/centre-annour",
    "countryCode": "FR",
    "timezone": "Europe/Paris",
    "image": "https://cdn.mawaqit.net/images/backend/mosque/643f114c-4c4c-4e4b-ab0a-7d6725756818/mosque/1eea8db7-31f5-6ba2-b224-066ed47a7584.jpg",
    "interiorPicture": "https://cdn.mawaqit.net/images/backend/mosque/643f114c-4c4c-4e4b-ab0a-7d6725756818/mosque/1eea8db7-31f5-6ba2-b224-066ed47a7584.jpg",
    "exteriorPicture": "https://cdn.mawaqit.net/images/backend/mosque/643f114c-4c4c-4e4b-ab0a-7d6725756818/mosque/1eea8db7-3711-687a-81f9-066ed47a7584.jpg",
    "calendarUrl": "https://calendar.google.com/calendar/ical/614e8a4cb293fcfc093f481be59e9c588a6d507a49d1b341413f16f62741c5a4%40group.calendar.google.com/public/basic.ics"
  },
  "grande-mosquee-de-paris": {
    "latitude": 48.842208,
    "longitude": 2.3540974,
    "name": "GRANDE MOSQUÉE DE PARIS - Paris",
    "url": "https://mawaqit.net/fr/grande-mosquee-de-paris",
    "label": "GRANDE MOSQUÉE DE PARIS - Paris",
    "logo": null,
    "site": "https://www.grandemosqueedeparis.fr",
    "association": "Société des Habous et des Lieux Saints de l’Islam",
    "steamUrl": "",
    "scrapedAt": "2025-09-04T16:09:12.142873+02:00",
    "parking": false,
    "ablutions": true,
    "ramadanMeal": true,
    "otherInfo": null,
    "womenSpace": true,
    "janazaPrayer": true,
    "aidPrayer": true,
    "adultCourses": true,
    "childrenCourses": true,
    "handicapAccessibility": true,
    "paymentWebsite": "https://www.helloasso.com/associations/la-grande-mosquee-de-paris/formulaires/2",
    "countryCode": "FR",
    "timezone": "Europe/Paris",
    "image": "https://cdn.mawaqit.net/images/backend/mosque/05b4d393-fb76-4d9b-b2a4-f98ab4c4b64f/mosque/1eea8d8a-899e-6160-9fce-066ed47a7584.jpg",
    "interiorPicture": "https://cdn.mawaqit.net/images/backend/mosque/05b4d393-fb76-4d9b-b2a4-f98ab4c4b64f/mosque/1eea8d8a-899e-6160-9fce-066ed47a7584.jpg",
    "exteriorPicture": "https://cdn.mawaqit.net/images/backend/mosque/05b4d393-fb76-4d9b-b2a4-f98ab4c4b64f/mosque/1eea8d8a-8e57-67f6-a525-066ed47a7584.jpg",
    "calendarUrl": "https://calendar.google.com/calendar/ical/3c173f44c870cc51da23bbd666909fa6967c8b6de3dd09ffda5e60368516bad4%40group.calendar.google.com/public/basic.ics"
  },
  "mosquee_falah_cachan": {
    "latitude": 48.7826999,
    "longitude": 2.3260244,
    "name": "Mosquée El Falah - Cachan",
    "url": "https://mawaqit.net/fr/mosquee-falah-cachan",
    "label": "Mosquée El Falah - Cachan",
    "logo": null,
    "site": "https://mosqueedecachan.fr/",
    "association": "Centre Culturel Musulman de Cachan",
    "steamUrl": "",
    "scrapedAt": "2025-09-20T16:49:12.244211+02:00",
    "parking": false,
    "ablutions": true,
    "ramadanMeal": false,
    "otherInfo": "https://www.mosqueedecachan.fr/?fbclid=IwY2xjawI1rr5leHRuA2FlbQEwAGFkaWQBqxeTPLxi2AEdi5JYnn_SE32gQRSIb_GlOLMCpHmEO4kLMPJWPxTfjy1owzXQbNzBqNBE_aem_wJdkmZU4BoSyhPoUyrBhPg&utm_medium=paid&utm_source=fb&u",
    "womenSpace": true,
    "janazaPrayer": false,
    "aidPrayer": true,
    "adultCourses": false,
    "childrenCourses": false,
    "handicapAccessibility": true,
    "paymentWebsite": "https://mosqueedecachan.fr/",
    "countryCode": "FR",
    "timezone": "Europe/Paris",
    "image": "https://cdn.mawaqit.net/images/backend/mosque_default_picture.png",
    "interiorPicture": "https://cdn.mawaqit.net/images/backend/mosque_default_picture.png",
    "exteriorPicture": "https://cdn.mawaqit.net/images/backend/mosque_default_interior_picture.png",
    "calendarUrl": "https://calendar.google.com/calendar/ical/e887bef473f403391a9d29a4ccde30e5a18d25f949fae7f6a934fe17f2d7f609@group.calendar.google.com/public/basic.ics"
  },
  "mosquee_essalam_merignac": {
    "latitude": 44.8479762,
    "longitude": -0.6851826,
    "name": "مسجد السلام - Mérignac",
    "url": "https://mawaqit.net/fr/mosquee-essalam-merignac",
    "label": "مسجد السلام - Mérignac",
    "logo": null,
    "site": "https://www.mosquee-merignac.fr",
    "association": "Association Mérignacaise des Musulmans",
    "steamUrl": "",
    "scrapedAt": "2025-09-20T17:00:35.559388+02:00",
    "parking": true,
    "ablutions": true,
    "ramadanMeal": false,
    "otherInfo": null,
    "womenSpace": true,
    "janazaPrayer": true,
    "aidPrayer": true,
    "adultCourses": true,
    "childrenCourses": true,
    "handicapAccessibility": true,
    "paymentWebsite": null,
    "countryCode": "FR",
    "timezone": "Europe/Paris",
    "image": "https://cdn.mawaqit.net/images/backend/mosque/2d683f99-7a5b-461d-b8bf-54c3e3b2e624/mosque/1eea8d88-72f4-6f2e-a957-066ed47a7584.jpg",
    "interiorPicture": "https://cdn.mawaqit.net/images/backend/mosque/2d683f99-7a5b-461d-b8bf-54c3e3b2e624/mosque/1eea8d88-72f4-6f2e-a957-066ed47a7584.jpg",
    "exteriorPicture": "https://cdn.mawaqit.net/images/backend/mosque/2d683f99-7a5b-461d-b8bf-54c3e3b2e624/mosque/1eea8d88-7734-672e-b102-066ed47a7584.jpg",
    "calendarUrl": "https://calendar.google.com/calendar/ical/7494792f250816b42a3ebcfea21590f78a9ccec4466f6a36de8d686083a5aa0b@group.calendar.google.com/public/basic.ics"
  },
  "mosquee_d_orly": {
    "latitude": 48.751004766535,
    "longitude": 2.4132464826107,
    "name": "Mosquée d'Orly",
    "url": "https://mawaqit.net/fr/mosquee-d-orly",
    "label": "Mosquée d'Orly",
    "logo": "https://cdn.mawaqit.net/images/backend/mosque/6984cbd4-56ad-4825-8e5a-9237cd83ddaf/mosque/1eea8d88-806e-6f56-8099-066ed47a7584.png",
    "site": "https://ascm-orly.fr/",
    "association": "ASCM - ASsociation Cultuelle des Musulmans",
    "steamUrl": null,
    "scrapedAt": "2025-09-20T17:09:48.089519+02:00",
    "parking": false,
    "ablutions": true,
    "ramadanMeal": true,
    "otherInfo": "Ouverture 30 minutes avant les prières\r\nFermeture 30 minutes après les prières",
    "womenSpace": true,
    "janazaPrayer": false,
    "aidPrayer": true,
    "adultCourses": true,
    "childrenCourses": true,
    "handicapAccessibility": true,
    "paymentWebsite": "https://www.helloasso.com/associations/ascm-mosquee-d-orly/formulaires/1",
    "countryCode": "FR",
    "timezone": "Europe/Paris",
    "image": "https://cdn.mawaqit.net/images/backend/mosque/6984cbd4-56ad-4825-8e5a-9237cd83ddaf/mosque/1eea8d88-8543-6518-8f23-066ed47a7584.JPG",
    "interiorPicture": "https://cdn.mawaqit.net/images/backend/mosque/6984cbd4-56ad-4825-8e5a-9237cd83ddaf/mosque/1eea8d88-8543-6518-8f23-066ed47a7584.JPG",
    "exteriorPicture": "https://cdn.mawaqit.net/images/backend/mosque/6984cbd4-56ad-4825-8e5a-9237cd83ddaf/mosque/1eea8d88-8a96-6772-ad3d-066ed47a7584.jpg",
    "calendarUrl": "https://calendar.google.com/calendar/ical/928b8c57f25add23a4ade0fd26df0e423471ed55eadff84f3cfbc5723262d871@group.calendar.google.com/public/basic.ics"
  },
  "mosquee_rahma_vitry_sur_seine": {
    "latitude": 48.7841682,
    "longitude": 2.4043068,
    "name": "مسجد الرحمة - Vitry-Sur-Seine",
    "url": "https://mawaqit.net/fr/mosquee-rahma-vitry-sur-seine",
    "label": "مسجد الرحمة - Vitry-Sur-Seine",
    "logo": "https://cdn.mawaqit.net/images/backend/mosque/13151ed0-c2cd-4ebc-81f7-0e456284928e/mosque/1eea8d88-941b-67fc-b408-066ed47a7584.png",
    "site": null,
    "association": "Association Masdjid Rahma",
    "steamUrl": "",
    "scrapedAt": "2025-09-20T17:13:26.675552+02:00",
    "parking": false,
    "ablutions": true,
    "ramadanMeal": true,
    "otherInfo": "La prière du vendredi est à 13h00 toute l’année.\r\nIl n’y pas de salle disponible pour les sœurs.",
    "womenSpace": false,
    "janazaPrayer": true,
    "aidPrayer": true,
    "adultCourses": true,
    "childrenCourses": false,
    "handicapAccessibility": false,
    "paymentWebsite": null,
    "countryCode": "FR",
    "timezone": "Europe/Paris",
    "image": "https://cdn.mawaqit.net/images/backend/mosque/13151ed0-c2cd-4ebc-81f7-0e456284928e/mosque/1eea8d88-98bd-6314-8f30-066ed47a7584.jpg",
    "interiorPicture": "https://cdn.mawaqit.net/images/backend/mosque/13151ed0-c2cd-4ebc-81f7-0e456284928e/mosque/1eea8d88-98bd-6314-8f30-066ed47a7584.jpg",
    "exteriorPicture": "https://cdn.mawaqit.net/images/backend/mosque/13151ed0-c2cd-4ebc-81f7-0e456284928e/mosque/1eea8d88-9db3-695e-9476-066ed47a7584.jpg",
    "calendarUrl": "https://calendar.google.com/calendar/ical/5f28985c9d7b9e8b59a3dd04f86da3884d03e783e285c7b016974b9434ef67c1@group.calendar.google.com/public/basic.ics"
  },
  "mosquee_essunna_houilles": {
    "latitude": 48.9278633,
    "longitude": 2.180074,
    "name": "Masjid Essunna - Houilles",
    "url": "https://mawaqit.net/fr/mosquee-essunna-houilles",
    "label": "Masjid Essunna - Houilles",
    "logo": null,
    "site": null,
    "association": "Association SFI",
    "steamUrl": "",
    "scrapedAt": "2025-09-20T17:02:39.204338+02:00",
    "parking": false,
    "ablutions": true,
    "ramadanMeal": false,
    "otherInfo": "ATTENTION Veuillez vous garer convenablement à l’extérieur de la cour.",
    "womenSpace": false,
    "janazaPrayer": false,
    "aidPrayer": true,
    "adultCourses": false,
    "childrenCourses": false,
    "handicapAccessibility": true,
    "paymentWebsite": null,
    "countryCode": "FR",
    "timezone": "Europe/Paris",
    "image": "https://cdn.mawaqit.net/images/backend/mosque_default_picture.png",
    "interiorPicture": "https://cdn.mawaqit.net/images/backend/mosque_default_picture.png",
    "exteriorPicture": "https://cdn.mawaqit.net/images/backend/mosque/90f77fb9-8cab-45df-9c42-1951ab7ff56c/mosque/1eea8d88-a78e-632a-82ff-066ed47a7584.jpg",
    "calendarUrl": "https://calendar.google.com/calendar/ical/5d424948b6d5670e92a802d8809cc3848d607619a38d8c0d50395e2c0810ce1f@group.calendar.google.com/public/basic.ics"
  },
  "mosquee_al_niya_romainville": {
    "latitude": 48.8916984,
    "longitude": 2.4337908,
    "name": "Mosquée Al Niya - Romainville",
    "url": "https://mawaqit.net/fr/mosquee-al-niya-romainville",
    "label": "Mosquée Al Niya - Romainville",
    "logo": null,
    "site": null,
    "association": "Association AFMR",
    "steamUrl": "",
    "scrapedAt": "2025-09-20T17:04:37.988026+02:00",
    "parking": true,
    "ablutions": true,
    "ramadanMeal": false,
    "otherInfo": null,
    "womenSpace": true,
    "janazaPrayer": false,
    "aidPrayer": true,
    "adultCourses": false,
    "childrenCourses": false,
    "handicapAccessibility": true,
    "paymentWebsite": null,
    "countryCode": "FR",
    "timezone": "Europe/Paris",
    "image": "https://cdn.mawaqit.net/images/backend/mosque_default_picture.png",
    "interiorPicture": "https://cdn.mawaqit.net/images/backend/mosque_default_picture.png",
    "exteriorPicture": "https://cdn.mawaqit.net/images/backend/mosque/c2b4363b-1016-4147-b294-2058c003c5dd/mosque/1eea8d88-b1ee-6c5c-8b90-066ed47a7584.jpg",
    "calendarUrl": "https://calendar.google.com/calendar/ical/14ed43807102fee683dfc6212424e2bbe233697e33ec424d527786570a282847@group.calendar.google.com/public/basic.ics"
  },
  "mosquee_dignite_colombes": {
    "latitude": 48.9233906,
    "longitude": 2.2368856,
    "name": "Mosquée Dignité - Colombes",
    "url": "https://mawaqit.net/fr/mosquee-dignite-colombes",
    "label": "Mosquée Dignité - Colombes",
    "logo": null,
    "site": null,
    "association": "Association MUSC",
    "steamUrl": "",
    "scrapedAt": "2025-09-20T17:17:03.212799+02:00",
    "parking": false,
    "ablutions": true,
    "ramadanMeal": true,
    "otherInfo": null,
    "womenSpace": true,
    "janazaPrayer": true,
    "aidPrayer": true,
    "adultCourses": true,
    "childrenCourses": true,
    "handicapAccessibility": true,
    "paymentWebsite": "https://helloasso.com/associations/musc/formulaires/4",
    "countryCode": "FR",
    "timezone": "Europe/Paris",
    "image": "https://cdn.mawaqit.net/images/backend/mosque_default_picture.png",
    "interiorPicture": "https://cdn.mawaqit.net/images/backend/mosque_default_picture.png",
    "exteriorPicture": "https://cdn.mawaqit.net/images/backend/mosque_default_interior_picture.png",
    "calendarUrl": "https://calendar.google.com/calendar/ical/8c9e866fa72339f2a13bb9ae59a039c9f57616b33befdc744ad1e05f58a1f45a@group.calendar.google.com/public/basic.ics"
  },
  "mosqueederueil": {
    "latitude": 48.8640652,
    "longitude": 2.1952244,
    "name": "Mosquée de Rueil-Malmaison - Malmaison",
    "url": "https://mawaqit.net/fr/mosqueederueil",
    "label": "Mosquée de Rueil-Malmaison - Malmaison",
    "logo": null,
    "site": null,
    "association": "Le Centre Culturel Musulman est là pour répondre à toutes vos questions et vous accompagner.",
    "steamUrl": "",
    "scrapedAt": "2025-09-20T17:20:21.177634+02:00",
    "parking": true,
    "ablutions": true,
    "ramadanMeal": true,
    "otherInfo": "(Ouverture 30 minutes avant chaque prière - Fermeture 30 minutes après chaque prière - Ouverture en continue entre les prières de Maghreb et Icha - Ouverture dès 11h00 le vendredi)",
    "womenSpace": true,
    "janazaPrayer": true,
    "aidPrayer": true,
    "adultCourses": true,
    "childrenCourses": true,
    "handicapAccessibility": true,
    "paymentWebsite": null,
    "countryCode": "FR",
    "timezone": "Europe/Paris",
    "image": "https://cdn.mawaqit.net/images/backend/mosque/c22619a7-374d-4392-a6bd-a772bd8ea7ce/mosque/1eea8d88-c157-66ee-9a6f-066ed47a7584.jpg",
    "interiorPicture": "https://cdn.mawaqit.net/images/backend/mosque/c22619a7-374d-4392-a6bd-a772bd8ea7ce/mosque/1eea8d88-c157-66ee-9a6f-066ed47a7584.jpg",
    "exteriorPicture": "https://cdn.mawaqit.net/images/backend/mosque/c22619a7-374d-4392-a6bd-a772bd8ea7ce/mosque/1eea8d88-c694-6ddc-96c4-066ed47a7584.jpg",
    "calendarUrl": "https://calendar.google.com/calendar/ical/02da72fb4c49076420456ebd1ebf6ca3b196d789c31a4f2f3f22591a8f201ecc@group.calendar.google.com/public/basic.ics"
  },
  "mosquee_ennour_laon_view_desktop": {
    "latitude": 49.5691978,
    "longitude": 3.644164,
    "name": "Mosquée Ennour - Laon",
    "url": "https://mawaqit.net/fr/mosquee-ennour-laon-view-desktop",
    "label": "Mosquée Ennour - Laon",
    "logo": null,
    "site": null,
    "association": "Association Cultuelle Islamique De Laon",
    "steamUrl": "",
    "scrapedAt": "2025-09-20T17:23:33.024537+02:00",
    "parking": false,
    "ablutions": true,
    "ramadanMeal": true,
    "otherInfo": null,
    "womenSpace": true,
    "janazaPrayer": true,
    "aidPrayer": true,
    "adultCourses": true,
    "childrenCourses": true,
    "handicapAccessibility": true,
    "paymentWebsite": null,
    "countryCode": "FR",
    "timezone": "Europe/Paris",
    "image": "https://cdn.mawaqit.net/images/backend/mosque/cb0d4697-9b5d-46cf-8d19-391313cd8f02/mosque/1eea8d88-d08b-6f20-8661-066ed47a7584.jpg",
    "interiorPicture": "https://cdn.mawaqit.net/images/backend/mosque/cb0d4697-9b5d-46cf-8d19-391313cd8f02/mosque/1eea8d88-d08b-6f20-8661-066ed47a7584.jpg",
    "exteriorPicture": "https://cdn.mawaqit.net/images/backend/mosque/cb0d4697-9b5d-46cf-8d19-391313cd8f02/mosque/1eea8d88-d5ce-60dc-af26-066ed47a7584.jpg",
    "calendarUrl": "https://calendar.google.com/calendar/ical/14939b524817015fa219f64297cbd48cbd88cd36105552b632a4877880aba391@group.calendar.google.com/public/basic.ics"
  },
  "mosquee_al_ansar_aubervilliers": {
    "latitude": 48.913791,
    "longitude": 2.3884214,
    "name": "Mosquée Al Ansar - مسجد  الانصار",
    "url": "https://mawaqit.net/fr/mosquee-al-ansar-aubervilliers",
    "label": "Mosquée Al Ansar - مسجد  الانصار",
    "logo": null,
    "site": null,
    "association": "Association Ansar",
    "steamUrl": "",
    "scrapedAt": "2025-09-20T17:26:58.492938+02:00",
    "parking": false,
    "ablutions": true,
    "ramadanMeal": true,
    "otherInfo": null,
    "womenSpace": true,
    "janazaPrayer": true,
    "aidPrayer": false,
    "adultCourses": true,
    "childrenCourses": true,
    "handicapAccessibility": true,
    "paymentWebsite": null,
    "countryCode": "FR",
    "timezone": "Europe/Paris",
    "image": "https://cdn.mawaqit.net/images/backend/mosque_default_picture.png",
    "interiorPicture": "https://cdn.mawaqit.net/images/backend/mosque_default_picture.png",
    "exteriorPicture": "https://cdn.mawaqit.net/images/backend/mosque/560c3ffa-d0ea-4e89-9d28-3c548faf309f/mosque/1eea8d88-dfbf-6b0e-97ef-066ed47a7584.jpg",
    "calendarUrl": "https://calendar.google.com/calendar/ical/a2cca661a19e0a344d7ed60f790c888497293b51fe3cef05eb07b053dd502d0c@group.calendar.google.com/public/basic.ics"
  },
  "institut_ibn_badis_nanterre_92000_france": {
    "latitude": 48.8860972,
    "longitude": 2.2167333,
    "name": "Institut Ibn Badis - Nanterre",
    "url": "https://mawaqit.net/fr/institut-ibn-badis-nanterre-92000-france",
    "label": "Institut Ibn Badis - Nanterre",
    "logo": "https://cdn.mawaqit.net/images/backend/mosque/ad2bcc57-30c3-4df9-a47d-aedfe0c252f1/mosque/1eea8d88-e9fa-6dda-8568-066ed47a7584.png",
    "site": "https://www.institutibnbadis.com/",
    "association": "Association Irchad",
    "steamUrl": "",
    "scrapedAt": "2025-09-20T17:29:55.648608+02:00",
    "parking": false,
    "ablutions": true,
    "ramadanMeal": true,
    "otherInfo": null,
    "womenSpace": true,
    "janazaPrayer": true,
    "aidPrayer": true,
    "adultCourses": true,
    "childrenCourses": true,
    "handicapAccessibility": true,
    "paymentWebsite": "https://www.institutibnbadis.com/waqf-avenir",
    "countryCode": "FR",
    "timezone": "Europe/Paris",
    "image": "https://cdn.mawaqit.net/images/backend/mosque/ad2bcc57-30c3-4df9-a47d-aedfe0c252f1/mosque/1eea8d88-ee4a-6408-aeef-066ed47a7584.jpg",
    "interiorPicture": "https://cdn.mawaqit.net/images/backend/mosque/ad2bcc57-30c3-4df9-a47d-aedfe0c252f1/mosque/1eea8d88-ee4a-6408-aeef-066ed47a7584.jpg",
    "exteriorPicture": "https://cdn.mawaqit.net/images/backend/mosque_default_interior_picture.png",
    "calendarUrl": "https://calendar.google.com/calendar/ical/dd5fd07f63a4c7163d39785dd104d20e647e35056b850bdc58107203a862bc5b@group.calendar.google.com/public/basic.ics"
  },
  "mosquee_omar_ibn_khattab_bagneux": {
    "latitude": 48.7959109,
    "longitude": 2.316573,
    "name": "MOSQUÉE DE BAGNEUX - Bagneux",
    "url": "https://mawaqit.net/fr/mosquee-omar-ibn-khattab-bagneux",
    "label": "MOSQUÉE DE BAGNEUX - Bagneux",
    "logo": "https://cdn.mawaqit.net/images/backend/mosque/56c3dccf-9e09-44f0-acc0-bff91b4eb9ed/mosque/1eea8d88-f33a-6f76-8d10-066ed47a7584.png",
    "site": "http://mosqueebagneux.fr",
    "association": "ABMOSHS- Bagneux",
    "steamUrl": "https://youtu.be/TWcVt5WhJDc",
    "scrapedAt": "2025-09-20T17:33:23.304888+02:00",
    "parking": false,
    "ablutions": true,
    "ramadanMeal": true,
    "otherInfo": "Les portes s'ouvrent 20 minutes avant chaque prière",
    "womenSpace": true,
    "janazaPrayer": true,
    "aidPrayer": true,
    "adultCourses": true,
    "childrenCourses": true,
    "handicapAccessibility": true,
    "paymentWebsite": "https://mosqueebagneux.fr/dons",
    "countryCode": "FR",
    "timezone": "Europe/Paris",
    "image": "https://cdn.mawaqit.net/images/backend/mosque/56c3dccf-9e09-44f0-acc0-bff91b4eb9ed/mosque/1eea8d88-f7c1-6068-9250-066ed47a7584.jpg",
    "interiorPicture": "https://cdn.mawaqit.net/images/backend/mosque/56c3dccf-9e09-44f0-acc0-bff91b4eb9ed/mosque/1eea8d88-f7c1-6068-9250-066ed47a7584.jpg",
    "exteriorPicture": "https://cdn.mawaqit.net/images/backend/mosque/56c3dccf-9e09-44f0-acc0-bff91b4eb9ed/mosque/1eea8d88-fc81-6850-ad6b-066ed47a7584.jpg",
    "calendarUrl": "https://calendar.google.com/calendar/ical/a8093a3e703f6dbbc4737aa4b1cbfa2b5d29e6c1ce834e565146322c715a7d34@group.calendar.google.com/public/basic.ics"
  },
  "mosquee_salam_suresnes": {
    "latitude": 48.8754612,
    "longitude": 2.2274346,
    "name": "Mosquée Salam - Suresnes",
    "url": "https://mawaqit.net/fr/mosquee-salam-suresnes",
    "label": "Mosquée Salam - Suresnes",
    "logo": "https://cdn.mawaqit.net/images/backend/mosque/a6aba0e0-898b-42ae-a83a-f93407ba5591/mosque/1eea8d89-065a-6674-a6fd-066ed47a7584.png",
    "site": "http://www.mosqueesalamsuresnes.fr",
    "association": null,
    "steamUrl": "",
    "scrapedAt": "2025-09-20T17:36:28.874437+02:00",
    "parking": false,
    "ablutions": true,
    "ramadanMeal": true,
    "otherInfo": null,
    "womenSpace": true,
    "janazaPrayer": true,
    "aidPrayer": true,
    "adultCourses": true,
    "childrenCourses": true,
    "handicapAccessibility": true,
    "paymentWebsite": "https://www.mosqueesalamsuresnes.fr/dons/",
    "countryCode": "FR",
    "timezone": "Europe/Paris",
    "image": "https://cdn.mawaqit.net/images/backend/mosque/a6aba0e0-898b-42ae-a83a-f93407ba5591/mosque/1f076a94-433c-6e20-8c04-06ec6b6ca699.jpg",
    "interiorPicture": "https://cdn.mawaqit.net/images/backend/mosque/a6aba0e0-898b-42ae-a83a-f93407ba5591/mosque/1f076a94-433c-6e20-8c04-06ec6b6ca699.jpg",
    "exteriorPicture": "https://cdn.mawaqit.net/images/backend/mosque/a6aba0e0-898b-42ae-a83a-f93407ba5591/mosque/1f076a94-4a5d-677c-81f0-06ec6b6ca699.jpg",
    "calendarUrl": "https://calendar.google.com/calendar/ical/d730277d3225ee46f49b247d787db5386860679f15c51806349147c5317435b7@group.calendar.google.com/public/basic.ics"
  },
  "mosquee_okba_ibn_nafaa_nanterre": {
    "latitude": 48.9095439,
    "longitude": 2.2164656,
    "name": "Mosquée okba ibn Nafaa - Nanterre",
    "url": "https://mawaqit.net/fr/mosquee-okba-ibn-nafaa-nanterre",
    "label": "Mosquée okba ibn Nafaa - Nanterre",
    "logo": null,
    "site": null,
    "association": "Association Mosquée okba ibn Nafaa",
    "steamUrl": null,
    "scrapedAt": "2025-09-20T17:40:07.128298+02:00",
    "parking": false,
    "ablutions": true,
    "ramadanMeal": true,
    "otherInfo": null,
    "womenSpace": true,
    "janazaPrayer": true,
    "aidPrayer": true,
    "adultCourses": true,
    "childrenCourses": true,
    "handicapAccessibility": true,
    "paymentWebsite": "https://www.helloasso.com/associations/association-okba-ibn-naffa/formulaires/2",
    "countryCode": "FR",
    "timezone": "Europe/Paris",
    "image": "https://cdn.mawaqit.net/images/backend/mosque/f18eda2c-c56c-4634-a22c-8975279715d5/mosque/1eea8d89-18fc-6322-b471-066ed47a7584.jpg",
    "interiorPicture": "https://cdn.mawaqit.net/images/backend/mosque/f18eda2c-c56c-4634-a22c-8975279715d5/mosque/1eea8d89-18fc-6322-b471-066ed47a7584.jpg",
    "exteriorPicture": "https://cdn.mawaqit.net/images/backend/mosque/f18eda2c-c56c-4634-a22c-8975279715d5/mosque/1eea8d89-1db7-6c0e-8170-066ed47a7584.jpg",
    "calendarUrl": "https://calendar.google.com/calendar/ical/76b88a5c1b1e2cee1b6765cc79b001c714599f637451077da5c9ade246f1085c@group.calendar.google.com/public/basic.ics"
  },
  "mosquee_bilal_sucy_en_brie": {
    "latitude": 48.7750996,
    "longitude": 2.5265443,
    "name": "Mosquée Bilal - Sucy-en-Brie",
    "url": "https://mawaqit.net/fr/mosquee-bilal-sucy-en-brie",
    "label": "Mosquée Bilal - Sucy-en-Brie",
    "logo": "https://cdn.mawaqit.net/images/backend/mosque/46609bd7-cfa1-4ea0-b644-98edd7c934e2/mosque/1eea8d89-275e-68d4-8193-066ed47a7584.jpg",
    "site": "http://www.mosqueedesucy.fr",
    "association": "Association Culturelle des Musulmans de Sucy",
    "steamUrl": "UCtsduTvOugDR-gLdeVxagYw",
    "scrapedAt": "2025-09-20T17:42:58.952339+02:00",
    "parking": false,
    "ablutions": true,
    "ramadanMeal": false,
    "otherInfo": null,
    "womenSpace": true,
    "janazaPrayer": true,
    "aidPrayer": true,
    "adultCourses": true,
    "childrenCourses": true,
    "handicapAccessibility": true,
    "paymentWebsite": "https://www.helloasso.com/associations/association-culturelle-des-musulmans-de-sucy-en-brie/collectes/construction-de-la-mosquee-de-sucy-en-brie#tickets",
    "countryCode": "FR",
    "timezone": "Europe/Paris",
    "image": "https://cdn.mawaqit.net/images/backend/mosque/46609bd7-cfa1-4ea0-b644-98edd7c934e2/mosque/1eea8d89-2b8b-66b4-b209-066ed47a7584.jpg",
    "interiorPicture": "https://cdn.mawaqit.net/images/backend/mosque/46609bd7-cfa1-4ea0-b644-98edd7c934e2/mosque/1eea8d89-2b8b-66b4-b209-066ed47a7584.jpg",
    "exteriorPicture": "https://cdn.mawaqit.net/images/backend/mosque/46609bd7-cfa1-4ea0-b644-98edd7c934e2/mosque/1eea8d89-3043-6508-b30f-066ed47a7584.jpg",
    "calendarUrl": "https://calendar.google.com/calendar/ical/95e4563d06ebc1059bf6aaa069af07005c9d89676b2643589959f346bdb6a305@group.calendar.google.com/public/basic.ics"
  },
  "mosquee_tawhid_saint_jean_de_maurienne": {
    "latitude": 45.2726709,
    "longitude": 6.3520335,
    "name": "Mosquée Tawhid - St-Jean-De-Mne",
    "url": "https://mawaqit.net/fr/mosquee-tawhid-saint-jean-de-maurienne",
    "label": "Mosquée Tawhid - St-Jean-De-Mne",
    "logo": null,
    "site": null,
    "association": null,
    "steamUrl": "",
    "scrapedAt": "2025-09-20T17:46:02.341201+02:00",
    "parking": true,
    "ablutions": true,
    "ramadanMeal": false,
    "otherInfo": null,
    "womenSpace": true,
    "janazaPrayer": true,
    "aidPrayer": true,
    "adultCourses": false,
    "childrenCourses": true,
    "handicapAccessibility": true,
    "paymentWebsite": null,
    "countryCode": "FR",
    "timezone": "Europe/Paris",
    "image": "https://cdn.mawaqit.net/images/backend/mosque/f013f732-85c2-42ed-a6c1-b4baf6844a78/mosque/1eea8d89-3999-69f4-8f08-066ed47a7584.jpg",
    "interiorPicture": "https://cdn.mawaqit.net/images/backend/mosque/f013f732-85c2-42ed-a6c1-b4baf6844a78/mosque/1eea8d89-3999-69f4-8f08-066ed47a7584.jpg",
    "exteriorPicture": "https://cdn.mawaqit.net/images/backend/mosque/f013f732-85c2-42ed-a6c1-b4baf6844a78/mosque/1eea8d89-3e3d-6f96-95c9-066ed47a7584.jpg",
    "calendarUrl": "https://calendar.google.com/calendar/ical/5fd96dafcaa4ebe5e225b489cd0fce5aff059dd382b3afcf1d8262ec3ebb40ac@group.calendar.google.com/public/basic.ics"
  },
  "mosquee_amfar_fontenay_aux_roses": {
    "latitude": 48.7864463,
    "longitude": 2.2986044,
    "name": "Mosquée AMFAR - Fontenay-aux-roses",
    "url": "https://mawaqit.net/fr/mosquee-amfar-fontenay-aux-roses",
    "label": "Mosquée AMFAR - Fontenay-aux-roses",
    "logo": null,
    "site": null,
    "association": "Association AMFAR",
    "steamUrl": "",
    "scrapedAt": "2025-09-21T11:12:47.693249+02:00",
    "parking": true,
    "ablutions": true,
    "ramadanMeal": true,
    "otherInfo": null,
    "womenSpace": true,
    "janazaPrayer": true,
    "aidPrayer": true,
    "adultCourses": true,
    "childrenCourses": true,
    "handicapAccessibility": true,
    "paymentWebsite": null,
    "countryCode": "FR",
    "timezone": "Europe/Paris",
    "image": "https://cdn.mawaqit.net/images/backend/mosque_default_picture.png",
    "interiorPicture": "https://cdn.mawaqit.net/images/backend/mosque_default_picture.png",
    "exteriorPicture": "https://cdn.mawaqit.net/images/backend/mosque/cc7e01b8-299d-417d-a6f6-6364f6218cc6/mosque/1eea8d89-4279-677c-bb36-066ed47a7584.jpg",
    "calendarUrl": "https://calendar.google.com/calendar/ical/5bf06d6b5d4637a5ca78178709de9a6eb361a769bb40451a4a30cb25fbd2000a@group.calendar.google.com/public/basic.ics"
  },
  "mosquee_al_oumma_montreuil": {
    "latitude": 48.8693904,
    "longitude": 2.4609583,
    "name": "Mosquée Al Oumma - Montreuil",
    "url": "https://mawaqit.net/fr/mosquee-al-oumma-montreuil",
    "label": "Mosquée Al Oumma - Montreuil",
    "logo": "https://cdn.mawaqit.net/images/backend/mosque/6a0cce6e-7d34-45ed-a576-c6e7319772a6/mosque/1eea8d89-4ca6-6466-b1e4-066ed47a7584.png",
    "site": "https://www.mosqueedemontreuil.fr/",
    "association": "FCAMM",
    "steamUrl": "",
    "scrapedAt": "2025-09-21T11:17:00.916523+02:00",
    "parking": true,
    "ablutions": true,
    "ramadanMeal": true,
    "otherInfo": null,
    "womenSpace": true,
    "janazaPrayer": true,
    "aidPrayer": true,
    "adultCourses": true,
    "childrenCourses": true,
    "handicapAccessibility": true,
    "paymentWebsite": "https://www.helloasso.com/associations/fcamm/formulaires/3",
    "countryCode": "FR",
    "timezone": "Europe/Paris",
    "image": "https://cdn.mawaqit.net/images/backend/mosque/6a0cce6e-7d34-45ed-a576-c6e7319772a6/mosque/1eea8d89-5139-6820-9af4-066ed47a7584.jpg",
    "interiorPicture": "https://cdn.mawaqit.net/images/backend/mosque/6a0cce6e-7d34-45ed-a576-c6e7319772a6/mosque/1eea8d89-5139-6820-9af4-066ed47a7584.jpg",
    "exteriorPicture": "https://cdn.mawaqit.net/images/backend/mosque/6a0cce6e-7d34-45ed-a576-c6e7319772a6/mosque/1eea8d89-568a-6b58-9501-066ed47a7584.jpg",
    "calendarUrl": "https://calendar.google.com/calendar/ical/1ff9809f36d354c5fab57c476a5dacc2ad29ce049f55cf33371178c0788bdf72@group.calendar.google.com/public/basic.ics"
  },
  "mosquee_al_mouhsinine_villeneuve_saint_georges": {
    "latitude": 48.7352656,
    "longitude": 2.4539558,
    "name": "Al Mouhsinine - Villeneuve-Saint-Georges",
    "url": "https://mawaqit.net/fr/mosquee-al-mouhsinine-villeneuve-saint-georges",
    "label": "Al Mouhsinine - Villeneuve-Saint-Georges",
    "logo": null,
    "site": null,
    "association": "association cultuelle musulmane de villeneuve saint georges",
    "steamUrl": "",
    "scrapedAt": "2025-09-21T11:20:53.153985+02:00",
    "parking": false,
    "ablutions": true,
    "ramadanMeal": false,
    "otherInfo": null,
    "womenSpace": true,
    "janazaPrayer": true,
    "aidPrayer": true,
    "adultCourses": true,
    "childrenCourses": true,
    "handicapAccessibility": false,
    "paymentWebsite": null,
    "countryCode": "FR",
    "timezone": "Europe/Paris",
    "image": "https://cdn.mawaqit.net/images/backend/mosque_default_picture.png",
    "interiorPicture": "https://cdn.mawaqit.net/images/backend/mosque_default_picture.png",
    "exteriorPicture": "https://cdn.mawaqit.net/images/backend/mosque_default_interior_picture.png",
    "calendarUrl": "https://calendar.google.com/calendar/ical/3ba6e692102a156677146084a38e66b6d42dfe4a64770534d4335069e8872bdf@group.calendar.google.com/public/basic.ics"
  },
  "al_forqane_montreuil": {
    "latitude": 48.8566582,
    "longitude": 2.4227735,
    "name": "Mosquée Al Forqane - Montreuil",
    "url": "https://mawaqit.net/fr/al-forqane-montreuil",
    "label": "Mosquée Al Forqane - Montreuil",
    "logo": null,
    "site": "https://www.alforqane.net",
    "association": "ACEM",
    "steamUrl": "",
    "scrapedAt": "2025-09-21T11:24:53.931365+02:00",
    "parking": false,
    "ablutions": true,
    "ramadanMeal": false,
    "otherInfo": "Fermeture 15” après chaque prière",
    "womenSpace": false,
    "janazaPrayer": true,
    "aidPrayer": true,
    "adultCourses": false,
    "childrenCourses": false,
    "handicapAccessibility": false,
    "paymentWebsite": "https://paypal.me/alforqane",
    "countryCode": "FR",
    "timezone": "Europe/Paris",
    "image": "https://cdn.mawaqit.net/images/backend/mosque_default_picture.png",
    "interiorPicture": "https://cdn.mawaqit.net/images/backend/mosque_default_picture.png",
    "exteriorPicture": "https://cdn.mawaqit.net/images/backend/mosque/b0b5ba4b-d4c9-4ff1-b65e-180d267731d6/mosque/1eea8d89-60ca-68c0-95cf-066ed47a7584.jpg",
    "calendarUrl": "https://calendar.google.com/calendar/ical/7e97063ebf8cc918018bd05bf50c2333df64a70f21f7a2b879a49ba79213b22f@group.calendar.google.com/public/basic.ics"
  },
  "mosquee_de_choisy_le_roi_choisy_le_roi": {
    "latitude": 48.7722584,
    "longitude": 2.4069785,
    "name": "AMC Mosquée de Choisy-Le-Roi - Choisy-le-Roi",
    "url": "https://mawaqit.net/fr/mosquee-de-choisy-le-roi-choisy-le-roi",
    "label": "AMC Mosquée de Choisy-Le-Roi - Choisy-le-Roi",
    "logo": "https://cdn.mawaqit.net/images/backend/mosque/046a0f1e-1bed-474d-902a-f29321178c17/mosque/1effcf85-276c-6c42-86a9-06ef9144e88f.png",
    "site": "http://www.mosquee-choisy.com/",
    "association": "Association des Musulmans Choisyens",
    "steamUrl": "",
    "scrapedAt": "2025-09-21T11:28:54.177419+02:00",
    "parking": false,
    "ablutions": true,
    "ramadanMeal": true,
    "otherInfo": "Votre mosquée ouvre ses portes 30 min avant chaque Salat et fermera ses portes 30 min après la Salat",
    "womenSpace": true,
    "janazaPrayer": true,
    "aidPrayer": true,
    "adultCourses": true,
    "childrenCourses": true,
    "handicapAccessibility": true,
    "paymentWebsite": "https://www.paypal.com/donate/?hosted_button_id=EYYCPH2RBVVJC",
    "countryCode": "FR",
    "timezone": "Europe/Paris",
    "image": "https://cdn.mawaqit.net/images/backend/mosque_default_picture.png",
    "interiorPicture": "https://cdn.mawaqit.net/images/backend/mosque_default_picture.png",
    "exteriorPicture": "https://cdn.mawaqit.net/images/backend/mosque_default_interior_picture.png",
    "calendarUrl": "https://calendar.google.com/calendar/ical/b113b8e48da9ed5eae6c4ed2c89881770ad015bb1d157638cc96485121432217@group.calendar.google.com/public/basic.ics"
  },
  "mosquee_de_roissy_en_brie_roissy_en_brie": {
    "latitude": 48.791457206069,
    "longitude": 2.6454734802246,
    "name": "Mosquée de Roissy-en-brie - Roissy-en-brie",
    "url": "https://mawaqit.net/fr/mosquee-de-roissy-en-brie-roissy-en-brie",
    "label": "Mosquée de Roissy-en-brie - Roissy-en-brie",
    "logo": null,
    "site": "http://www.acmrb.com",
    "association": "ACMRB",
    "steamUrl": "",
    "scrapedAt": "2025-09-21T11:32:55.964024+02:00",
    "parking": true,
    "ablutions": true,
    "ramadanMeal": true,
    "otherInfo": null,
    "womenSpace": true,
    "janazaPrayer": true,
    "aidPrayer": true,
    "adultCourses": true,
    "childrenCourses": true,
    "handicapAccessibility": true,
    "paymentWebsite": null,
    "countryCode": "FR",
    "timezone": "Europe/Paris",
    "image": "https://cdn.mawaqit.net/images/backend/mosque_default_picture.png",
    "interiorPicture": "https://cdn.mawaqit.net/images/backend/mosque_default_picture.png",
    "exteriorPicture": "https://cdn.mawaqit.net/images/backend/mosque_default_interior_picture.png",
    "calendarUrl": "https://calendar.google.com/calendar/ical/4410ad674fbdaf4e392d830c9e7dd451b862815226bf39405be364a1f6794520@group.calendar.google.com/public/basic.ics"
  },
  "mosquee_de_gentilly_gentilly": {
    "latitude": 48.8083319,
    "longitude": 2.3475069,
    "name": "Mosquée de Gentilly UMG - Gentilly",
    "url": "https://mawaqit.net/fr/mosquee-de-gentilly-gentilly",
    "label": "Mosquée de Gentilly UMG - Gentilly",
    "logo": null,
    "site": null,
    "association": "Mosquée de Gentilly UMG",
    "steamUrl": "",
    "scrapedAt": "2025-09-21T11:36:57.613115+02:00",
    "parking": false,
    "ablutions": true,
    "ramadanMeal": false,
    "otherInfo": null,
    "womenSpace": true,
    "janazaPrayer": true,
    "aidPrayer": true,
    "adultCourses": true,
    "childrenCourses": true,
    "handicapAccessibility": false,
    "paymentWebsite": "https://www.helloasso.com/associations/union-des-musulmans-de-gentilly",
    "countryCode": "FR",
    "timezone": "Europe/Paris",
    "image": "https://cdn.mawaqit.net/images/backend/mosque_default_picture.png",
    "interiorPicture": "https://cdn.mawaqit.net/images/backend/mosque_default_picture.png",
    "exteriorPicture": "https://cdn.mawaqit.net/images/backend/mosque_default_interior_picture.png",
    "calendarUrl": "https://calendar.google.com/calendar/ical/bd33ec3caba72a8077178d1bbd8246b9a54d64eec87732008fb56ed30f5f6a7c@group.calendar.google.com/public/basic.ics"
  },
  "mosquee_addawa_msjd_ld_w_paris": {
    "latitude": 48.887393547357,
    "longitude": 2.3699355125427,
    "name": "Mosquée Adda'wa - Stalingrad",
    "url": "https://mawaqit.net/fr/mosquee-addawa-msjd-ld-w-paris",
    "label": "Mosquée Adda'wa - Stalingrad",
    "logo": "https://cdn.mawaqit.net/images/backend/mosque/61a9e194-f934-46c7-bb15-15658b41e125/mosque/1eeebb1e-9ae5-6be2-8c97-060bd329544b.png",
    "site": "https://mosqueeaddawa.fr/",
    "association": "ACIMA",
    "steamUrl": "",
    "scrapedAt": "2025-09-21T11:41:52.649335+02:00",
    "parking": false,
    "ablutions": true,
    "ramadanMeal": false,
    "otherInfo": "Iqama 10 minutes après adhan sauf pour salât al’maghreb",
    "womenSpace": true,
    "janazaPrayer": true,
    "aidPrayer": true,
    "adultCourses": false,
    "childrenCourses": false,
    "handicapAccessibility": true,
    "paymentWebsite": "https://www.myamana.fr/portail?asso=association-cultuelle-islamique-mosquee-addawa",
    "countryCode": "FR",
    "timezone": "Europe/Paris",
    "image": "https://cdn.mawaqit.net/images/backend/mosque_default_picture.png",
    "interiorPicture": "https://cdn.mawaqit.net/images/backend/mosque_default_picture.png",
    "exteriorPicture": "https://cdn.mawaqit.net/images/backend/mosque_default_interior_picture.png",
    "calendarUrl": "https://calendar.google.com/calendar/ical/afc7d97d60e3ac233708159d7d542166cd916ea40a04e93e7af8569daeeceb67@group.calendar.google.com/public/basic.ics"
  },
  "foyer_david_dangers_paris": {
    "latitude": 48.8827648,
    "longitude": 2.3903209,
    "name": "Foyer David D'angers - Paris",
    "url": "https://mawaqit.net/fr/foyer-david-dangers-paris",
    "label": "Foyer David D'angers - Paris",
    "logo": null,
    "site": null,
    "association": null,
    "steamUrl": "",
    "scrapedAt": "2025-09-21T11:46:04.316006+02:00",
    "parking": false,
    "ablutions": false,
    "ramadanMeal": false,
    "otherInfo": null,
    "womenSpace": false,
    "janazaPrayer": false,
    "aidPrayer": false,
    "adultCourses": false,
    "childrenCourses": false,
    "handicapAccessibility": false,
    "paymentWebsite": null,
    "countryCode": "FR",
    "timezone": "Europe/Paris",
    "image": "https://cdn.mawaqit.net/images/backend/mosque_default_picture.png",
    "interiorPicture": "https://cdn.mawaqit.net/images/backend/mosque_default_picture.png",
    "exteriorPicture": "https://cdn.mawaqit.net/images/backend/mosque_default_interior_picture.png",
    "calendarUrl": "https://calendar.google.com/calendar/ical/6d533a8d06ff3778aa24c65d69be7b5d580a5a154d0c627957f20f6fb2d91b00@group.calendar.google.com/public/basic.ics"
  },
  "dzemat_paris_le_pre_saint_gervais_93500_france": {
    "latitude": 48.8872987,
    "longitude": 2.4040561,
    "name": "DŽEMAT BOSNIAQUE PARIS - LE PRE SAINT GERVAIS",
    "url": "https://mawaqit.net/fr/dzemat-paris-le-pre-saint-gervais-93500-france",
    "label": "DŽEMAT BOSNIAQUE PARIS - LE PRE SAINT GERVAIS",
    "logo": "https://cdn.mawaqit.net/images/backend/mosque/1e77008c-b54b-4a57-aa1c-627368cf8a42/mosque/1ef3b9f3-f32f-6f0e-974d-0eccd22c0f01.png",
    "site": "https://ccbf-paris.org/",
    "association": "CENTRE CULTUEL BOSNIAQUE",
    "steamUrl": null,
    "scrapedAt": "2025-09-21T11:50:03.550205+02:00",
    "parking": false,
    "ablutions": true,
    "ramadanMeal": false,
    "otherInfo": null,
    "womenSpace": true,
    "janazaPrayer": false,
    "aidPrayer": false,
    "adultCourses": true,
    "childrenCourses": true,
    "handicapAccessibility": false,
    "paymentWebsite": null,
    "countryCode": "FR",
    "timezone": "Europe/Paris",
    "image": "https://cdn.mawaqit.net/images/backend/mosque/1e77008c-b54b-4a57-aa1c-627368cf8a42/mosque/1ef37aef-90ec-6628-8f1f-0eccd22c0f01.jpeg",
    "interiorPicture": "https://cdn.mawaqit.net/images/backend/mosque/1e77008c-b54b-4a57-aa1c-627368cf8a42/mosque/1ef37aef-90ec-6628-8f1f-0eccd22c0f01.jpeg",
    "exteriorPicture": "https://cdn.mawaqit.net/images/backend/mosque/1e77008c-b54b-4a57-aa1c-627368cf8a42/mosque/1ef37aef-9b76-68d2-a19f-0eccd22c0f01.jpeg",
    "calendarUrl": "https://calendar.google.com/calendar/ical/91b2e74aeeef62bf2e4a4e5fbbf093a8ade393a7bf5fa8ae2f6a38ccd8012662@group.calendar.google.com/public/basic.ics"
  },
  "mosquee_thionville": {
    "latitude": 49.3707947,
    "longitude": 6.151587,
    "name": "Mosquée de THIONVILLE - THIONVILLE",
    "url": "https://mawaqit.net/fr/mosquee-thionville",
    "label": "Mosquée de THIONVILLE - THIONVILLE",
    "logo": null,
    "site": "http://mosqueethionville.fr/",
    "association": "Association des Musulmans de Thionville",
    "steamUrl": "",
    "scrapedAt": "2025-09-21T17:33:22.363144+02:00",
    "parking": true,
    "ablutions": true,
    "ramadanMeal": true,
    "otherInfo": null,
    "womenSpace": true,
    "janazaPrayer": true,
    "aidPrayer": true,
    "adultCourses": true,
    "childrenCourses": true,
    "handicapAccessibility": true,
    "paymentWebsite": null,
    "countryCode": "FR",
    "timezone": "Europe/Paris",
    "image": "https://cdn.mawaqit.net/images/backend/mosque_default_picture.png",
    "interiorPicture": "https://cdn.mawaqit.net/images/backend/mosque_default_picture.png",
    "exteriorPicture": "https://cdn.mawaqit.net/images/backend/mosque_default_interior_picture.png",
    "calendarUrl": "https://calendar.google.com/calendar/ical/69653ff9960696f1c2a5212ff3f8763ff44631b8a57443a9a5b9050f42ef5f59@group.calendar.google.com/public/basic.ics"
  },
  "al_arqam_epinay_sur_seine": {
    "latitude": 48.9556145,
    "longitude": 2.3259978,
    "name": "Dar Al Arqam - Epinay-sur-Seine",
    "url": "https://mawaqit.net/fr/al-arqam-epinay-sur-seine",
    "label": "Dar Al Arqam - Epinay-sur-Seine",
    "logo": null,
    "site": "http://www.masjidalarqam.com",
    "association": "AME",
    "steamUrl": "",
    "scrapedAt": "2025-09-21T17:36:23.917964+02:00",
    "parking": false,
    "ablutions": false,
    "ramadanMeal": false,
    "otherInfo": null,
    "womenSpace": true,
    "janazaPrayer": false,
    "aidPrayer": false,
    "adultCourses": false,
    "childrenCourses": false,
    "handicapAccessibility": false,
    "paymentWebsite": null,
    "countryCode": "FR",
    "timezone": "Europe/Paris",
    "image": "https://cdn.mawaqit.net/images/backend/mosque/bcbc711c-ffad-4d76-8aa0-30bb70e44bc8/mosque/1eea8d89-6de5-64b0-b3f3-066ed47a7584.jpg",
    "interiorPicture": "https://cdn.mawaqit.net/images/backend/mosque/bcbc711c-ffad-4d76-8aa0-30bb70e44bc8/mosque/1eea8d89-6de5-64b0-b3f3-066ed47a7584.jpg",
    "exteriorPicture": "https://cdn.mawaqit.net/images/backend/mosque/bcbc711c-ffad-4d76-8aa0-30bb70e44bc8/mosque/1eea8d89-72e2-65d0-bec1-066ed47a7584.jpg",
    "calendarUrl": "https://calendar.google.com/calendar/ical/3eb8313cf736fc81fbace80891a6b1ecd00c776f4306336df9b21da3299a9304@group.calendar.google.com/public/basic.ics"
  },
  "mosquee_assalam_maisons_alfort_1": {
    "latitude": 48.7883461,
    "longitude": 2.4328842,
    "name": "Mosquée AsSalam - Maisons-Alfort",
    "url": "https://mawaqit.net/fr/mosquee-assalam-maisons-alfort-1",
    "label": "Mosquée AsSalam - Maisons-Alfort",
    "logo": "https://cdn.mawaqit.net/images/backend/mosque/072b6b2c-cdbe-48da-9d59-e2e35a0d765b/mosque/1efc8752-dd30-65b6-bcae-0a21b15e7a1f.jpg",
    "site": "http://acmma.fr/",
    "association": "ACMMA",
    "steamUrl": "",
    "scrapedAt": "2025-09-21T17:51:31.981587+02:00",
    "parking": false,
    "ablutions": true,
    "ramadanMeal": false,
    "otherInfo": null,
    "womenSpace": true,
    "janazaPrayer": true,
    "aidPrayer": true,
    "adultCourses": false,
    "childrenCourses": false,
    "handicapAccessibility": true,
    "paymentWebsite": "http://paypal.me/mosqueeassalam",
    "countryCode": "FR",
    "timezone": "Europe/Paris",
    "image": "https://cdn.mawaqit.net/images/backend/mosque_default_picture.png",
    "interiorPicture": "https://cdn.mawaqit.net/images/backend/mosque_default_picture.png",
    "exteriorPicture": "https://cdn.mawaqit.net/images/backend/mosque_default_interior_picture.png",
    "calendarUrl": "https://calendar.google.com/calendar/ical/83c8eafd9646f62269281153a148ec019c11d1fcfee0023c7292dea0164a0156@group.calendar.google.com/public/basic.ics"
  },
  "mosquee_el_asr_antony": {
    "latitude": 48.7381824,
    "longitude": 2.2877266,
    "name": "Mosquée EL-ASR EPOQUE - Antony",
    "url": "https://mawaqit.net/fr/mosquee-el-asr-antony",
    "label": "Mosquée EL-ASR EPOQUE - Antony",
    "logo": null,
    "site": null,
    "association": null,
    "steamUrl": "",
    "scrapedAt": "2025-09-21T17:55:22.522234+02:00",
    "parking": true,
    "ablutions": true,
    "ramadanMeal": true,
    "otherInfo": null,
    "womenSpace": true,
    "janazaPrayer": true,
    "aidPrayer": true,
    "adultCourses": true,
    "childrenCourses": true,
    "handicapAccessibility": true,
    "paymentWebsite": "https://www.apayer.fr/epoqueelasr",
    "countryCode": "FR",
    "timezone": "Europe/Paris",
    "image": "https://cdn.mawaqit.net/images/backend/mosque/4df0b1ca-47d5-45a9-a9d4-4bd4ba2a7f5e/mosque/1eea8d89-7be5-66f0-b98e-066ed47a7584.jpg",
    "interiorPicture": "https://cdn.mawaqit.net/images/backend/mosque/4df0b1ca-47d5-45a9-a9d4-4bd4ba2a7f5e/mosque/1eea8d89-7be5-66f0-b98e-066ed47a7584.jpg",
    "exteriorPicture": "https://cdn.mawaqit.net/images/backend/mosque/4df0b1ca-47d5-45a9-a9d4-4bd4ba2a7f5e/mosque/1eea8d89-80e1-678a-b604-066ed47a7584.jpg",
    "calendarUrl": "https://calendar.google.com/calendar/ical/6f511b67f002095bbfaffd7471cacb01c7d61f03587e254d04da4f3f3c6fdddf@group.calendar.google.com/public/basic.ics"
  },
  "mosquee_d_alfortville_alfortville": {
    "latitude": 48.7828834,
    "longitude": 2.4293869,
    "name": "Mosquée d'Alfortville - Alfortville",
    "url": "https://mawaqit.net/fr/mosquee-d-alfortville-alfortville",
    "label": "Mosquée d'Alfortville - Alfortville",
    "logo": null,
    "site": null,
    "association": "Association Musulmane d'Alfortville",
    "steamUrl": "",
    "scrapedAt": "2025-09-21T17:59:22.750923+02:00",
    "parking": false,
    "ablutions": true,
    "ramadanMeal": false,
    "otherInfo": null,
    "womenSpace": true,
    "janazaPrayer": false,
    "aidPrayer": true,
    "adultCourses": true,
    "childrenCourses": true,
    "handicapAccessibility": true,
    "paymentWebsite": null,
    "countryCode": "FR",
    "timezone": "Europe/Paris",
    "image": "https://cdn.mawaqit.net/images/backend/mosque/15e92c02-8b83-4869-ab75-f7089341a1a4/mosque/1eea8d89-8522-63b2-acac-066ed47a7584.jpg",
    "interiorPicture": "https://cdn.mawaqit.net/images/backend/mosque/15e92c02-8b83-4869-ab75-f7089341a1a4/mosque/1eea8d89-8522-63b2-acac-066ed47a7584.jpg",
    "exteriorPicture": "https://cdn.mawaqit.net/images/backend/mosque/15e92c02-8b83-4869-ab75-f7089341a1a4/mosque/1eea8d89-8a62-6cbe-be79-066ed47a7584.jpg",
    "calendarUrl": "https://calendar.google.com/calendar/ical/7044b914e00252e37d9fd0f25684a6013ffee7d80e5d8f23bbfca048d1ad65f2@group.calendar.google.com/public/basic.ics"
  },
  "mosquee_andalus_chatenay_malabry": {
    "latitude": 48.7679057,
    "longitude": 2.2565312,
    "name": "Mosquée Andalus - Châtenay-Malabry",
    "url": "https://mawaqit.net/fr/mosquee-andalus-chatenay-malabry",
    "label": "Mosquée Andalus - Châtenay-Malabry",
    "logo": "https://cdn.mawaqit.net/images/backend/mosque/4af6a36a-0811-473f-bf01-a0abae8cf09b/mosque/1eea8d89-931a-6276-986c-066ed47a7584.jpg",
    "site": "http://www.andalus92.fr",
    "association": "Institut Andalus",
    "steamUrl": "",
    "scrapedAt": "2025-09-21T18:03:29.118054+02:00",
    "parking": true,
    "ablutions": true,
    "ramadanMeal": true,
    "otherInfo": "Ouverture : 20 min avant El Adhan\r\nFermeture : 10 min Après la prière\r\nDjoumouaa : à,12h50. Accès limité à la capacité d'accueil.",
    "womenSpace": false,
    "janazaPrayer": true,
    "aidPrayer": true,
    "adultCourses": true,
    "childrenCourses": true,
    "handicapAccessibility": true,
    "paymentWebsite": null,
    "countryCode": "FR",
    "timezone": "Europe/Paris",
    "image": "https://cdn.mawaqit.net/images/backend/mosque/4af6a36a-0811-473f-bf01-a0abae8cf09b/mosque/1eea8d89-9741-6516-a8eb-066ed47a7584.jpg",
    "interiorPicture": "https://cdn.mawaqit.net/images/backend/mosque/4af6a36a-0811-473f-bf01-a0abae8cf09b/mosque/1eea8d89-9741-6516-a8eb-066ed47a7584.jpg",
    "exteriorPicture": "https://cdn.mawaqit.net/images/backend/mosque/4af6a36a-0811-473f-bf01-a0abae8cf09b/mosque/1eea8d89-9c62-636a-8622-066ed47a7584.jpg",
    "calendarUrl": "https://calendar.google.com/calendar/ical/3b2c7422e12f18bd9b30017bb936d20fc568d159a83661b76bceadccef018f2e@group.calendar.google.com/public/basic.ics"
  },
  "grande_mosquee_perpignan": {
    "latitude": 42.7289797,
    "longitude": 2.8829103,
    "name": "Grande Mosquée Perpignan",
    "url": "https://mawaqit.net/fr/grande-mosquee-perpignan",
    "label": "Grande Mosquée Perpignan",
    "logo": null,
    "site": "https://mawaqit.net/fr/grande-mosquee-perpignan",
    "association": "Collectif fraternité",
    "steamUrl": "",
    "scrapedAt": "2025-09-21T18:07:25.175392+02:00",
    "parking": true,
    "ablutions": true,
    "ramadanMeal": true,
    "otherInfo": null,
    "womenSpace": true,
    "janazaPrayer": true,
    "aidPrayer": true,
    "adultCourses": true,
    "childrenCourses": true,
    "handicapAccessibility": true,
    "paymentWebsite": null,
    "countryCode": "FR",
    "timezone": "Europe/Paris",
    "image": "https://cdn.mawaqit.net/images/backend/mosque_default_picture.png",
    "interiorPicture": "https://cdn.mawaqit.net/images/backend/mosque_default_picture.png",
    "exteriorPicture": "https://cdn.mawaqit.net/images/backend/mosque_default_interior_picture.png",
    "calendarUrl": "https://calendar.google.com/calendar/ical/8777b99ae059365e0b61d10e9fed8dc65c9fe098bcae6662f7ea2d09bc7ca50e@group.calendar.google.com/public/basic.ics"
  },
  "m_valentigney": {
    "latitude": 47.4767635,
    "longitude": 6.8268851,
    "name": "مسجد الرحمة فالانتيني - Valentigney",
    "url": "https://mawaqit.net/fr/m-valentigney",
    "label": "مسجد الرحمة فالانتيني - Valentigney",
    "logo": null,
    "site": null,
    "association": "A.R.M.V",
    "steamUrl": "",
    "scrapedAt": "2025-09-21T18:11:25.678655+02:00",
    "parking": true,
    "ablutions": true,
    "ramadanMeal": true,
    "otherInfo": "La porte de la mosquée s'ouvre 10min avant chaque prière. À l'exception de la prière de vendredi la mosquée ouvre 30 min avant.",
    "womenSpace": true,
    "janazaPrayer": true,
    "aidPrayer": true,
    "adultCourses": true,
    "childrenCourses": true,
    "handicapAccessibility": true,
    "paymentWebsite": null,
    "countryCode": "FR",
    "timezone": "Europe/Paris",
    "image": "https://cdn.mawaqit.net/images/backend/mosque/405a8e54-2ab6-42be-b2fc-f2e74a096a79/mosque/1eea8d89-b40f-6d64-a96a-066ed47a7584.jpg",
    "interiorPicture": "https://cdn.mawaqit.net/images/backend/mosque/405a8e54-2ab6-42be-b2fc-f2e74a096a79/mosque/1eea8d89-b40f-6d64-a96a-066ed47a7584.jpg",
    "exteriorPicture": "https://cdn.mawaqit.net/images/backend/mosque/405a8e54-2ab6-42be-b2fc-f2e74a096a79/mosque/1eea8d89-b92b-6622-9cd3-066ed47a7584.jpg",
    "calendarUrl": "https://calendar.google.com/calendar/ical/f2d02c538bd2d840201fdfc349cb99bfc0b9a1ed6090625e72fb900a32c50ad3@group.calendar.google.com/public/basic.ics"
  },
  "mosquee_de_noisy_le_grand_noisy_le_grand": {
    "latitude": 48.841627626006,
    "longitude": 2.5791451334953,
    "name": "Mosquée du Champy - Noisy-le-grand",
    "url": "https://mawaqit.net/fr/mosquee-de-noisy-le-grand-noisy-le-grand",
    "label": "Mosquée du Champy - Noisy-le-grand",
    "logo": null,
    "site": null,
    "association": "Association MNLG",
    "steamUrl": "",
    "scrapedAt": "2025-09-21T18:15:17.776565+02:00",
    "parking": false,
    "ablutions": true,
    "ramadanMeal": true,
    "otherInfo": "Pas de stationnements disponible aux abords de la mosquée. \r\nUtiliser le parking public du centre commercial de Super U (5 minute à pied).",
    "womenSpace": true,
    "janazaPrayer": true,
    "aidPrayer": false,
    "adultCourses": true,
    "childrenCourses": true,
    "handicapAccessibility": true,
    "paymentWebsite": "https://www.helloasso.com/associations/musulmans-de-noisy-le-grand/formulaires/1",
    "countryCode": "FR",
    "timezone": "Europe/Paris",
    "image": "https://cdn.mawaqit.net/images/backend/mosque_default_picture.png",
    "interiorPicture": "https://cdn.mawaqit.net/images/backend/mosque_default_picture.png",
    "exteriorPicture": "https://cdn.mawaqit.net/images/backend/mosque/45c6fb9a-6832-4d92-9113-fb48ed0d4937/mosque/1eea8d89-c362-6f46-b488-066ed47a7584.png",
    "calendarUrl": "https://calendar.google.com/calendar/ical/b09c8eb793f241b686b18522c57b44a09553fee4c7d9af781d895894f15c52eb@group.calendar.google.com/public/basic.ics"
  },
  "mosquee_al_houda_antony": {
    "latitude": 48.731457629827,
    "longitude": 2.3040315491516,
    "name": "Mosquée Al-Houda - Antony",
    "url": "https://mawaqit.net/fr/mosquee-al-houda-antony",
    "label": "Mosquée Al-Houda - Antony",
    "logo": "https://cdn.mawaqit.net/images/backend/mosque/bc5bf639-dd6e-4650-9eea-a118f5211a07/mosque/1efe6fe9-4757-6a72-9261-063aa5df5c67.png",
    "site": "https://mosqueeantony.fr",
    "association": "Espoir-Musulmans d'Antony",
    "steamUrl": "UCy9t-Ufi_J1wPp5FyIey8HA",
    "scrapedAt": "2025-09-21T18:19:30.559585+02:00",
    "parking": false,
    "ablutions": true,
    "ramadanMeal": true,
    "otherInfo": null,
    "womenSpace": true,
    "janazaPrayer": false,
    "aidPrayer": true,
    "adultCourses": true,
    "childrenCourses": true,
    "handicapAccessibility": true,
    "paymentWebsite": "https://mosqueeantony.fr/faire-un-don/?utm_source=mawaqit",
    "countryCode": "FR",
    "timezone": "Europe/Paris",
    "image": "https://cdn.mawaqit.net/images/backend/mosque/bc5bf639-dd6e-4650-9eea-a118f5211a07/mosque/1eea8d89-ccac-6dd6-a82c-066ed47a7584.jpeg",
    "interiorPicture": "https://cdn.mawaqit.net/images/backend/mosque/bc5bf639-dd6e-4650-9eea-a118f5211a07/mosque/1eea8d89-ccac-6dd6-a82c-066ed47a7584.jpeg",
    "exteriorPicture": "https://cdn.mawaqit.net/images/backend/mosque_default_interior_picture.png",
    "calendarUrl": "https://calendar.google.com/calendar/ical/0630c0ae372ecd4dd3ed98c88a389394a757ac89c74563cc833fea8c5cdae9dd@group.calendar.google.com/public/basic.ics"
  },
  "mosquee_as_salam_petit_couronne": {
    "latitude": 49.3847283,
    "longitude": 1.0203367,
    "name": "Mosquée AS-SALAM - Petit-Couronne",
    "url": "https://mawaqit.net/fr/mosquee-as-salam-petit-couronne",
    "label": "Mosquée AS-SALAM - Petit-Couronne",
    "logo": null,
    "site": null,
    "association": "Association Coopération Et Fraternité",
    "steamUrl": "",
    "scrapedAt": "2025-09-21T18:23:21.774255+02:00",
    "parking": true,
    "ablutions": true,
    "ramadanMeal": true,
    "otherInfo": null,
    "womenSpace": true,
    "janazaPrayer": true,
    "aidPrayer": true,
    "adultCourses": true,
    "childrenCourses": true,
    "handicapAccessibility": true,
    "paymentWebsite": null,
    "countryCode": "FR",
    "timezone": "UTC",
    "image": "https://cdn.mawaqit.net/images/backend/mosque/e8b3e34f-ae5e-4072-a9cf-47eb1d18fec6/mosque/1eea8d89-d660-67b0-97ba-066ed47a7584.jpg",
    "interiorPicture": "https://cdn.mawaqit.net/images/backend/mosque/e8b3e34f-ae5e-4072-a9cf-47eb1d18fec6/mosque/1eea8d89-d660-67b0-97ba-066ed47a7584.jpg",
    "exteriorPicture": "https://cdn.mawaqit.net/images/backend/mosque/e8b3e34f-ae5e-4072-a9cf-47eb1d18fec6/mosque/1eea8d89-db2a-6b74-bb5f-066ed47a7584.jpg",
    "calendarUrl": "https://calendar.google.com/calendar/ical/e1fe9ea8ee18733dcfbc09305237ca9923c960445cadbff87dc71d3c6796bdf2@group.calendar.google.com/public/basic.ics"
  },
  "mosquee_epinette_maubeuge": {
    "latitude": 50.2911418,
    "longitude": 3.9716188,
    "name": "Mosquée de l’Epinette - Maubeuge",
    "url": "https://mawaqit.net/fr/mosquee-epinette-maubeuge",
    "label": "Mosquée de l’Epinette - Maubeuge",
    "logo": null,
    "site": "https://mawaqit.net/fr/m/mosquee-epinette-maubeuge",
    "association": "Association A.S.P",
    "steamUrl": "",
    "scrapedAt": "2025-09-21T18:27:17.137236+02:00",
    "parking": true,
    "ablutions": true,
    "ramadanMeal": false,
    "otherInfo": "Chaîne YouTube https://www.youtube.com/channel/UCiDCDwoJv47q7TRDbX_d5Fw",
    "womenSpace": true,
    "janazaPrayer": false,
    "aidPrayer": true,
    "adultCourses": true,
    "childrenCourses": true,
    "handicapAccessibility": true,
    "paymentWebsite": null,
    "countryCode": "FR",
    "timezone": "Europe/Paris",
    "image": "https://cdn.mawaqit.net/images/backend/mosque_default_picture.png",
    "interiorPicture": "https://cdn.mawaqit.net/images/backend/mosque_default_picture.png",
    "exteriorPicture": "https://cdn.mawaqit.net/images/backend/mosque_default_interior_picture.png",
    "calendarUrl": "https://calendar.google.com/calendar/ical/405aafda0956be52b8fe95ce1d4f26bb343951e94f0038dd9234ec182d7d5a0e@group.calendar.google.com/public/basic.ics"
  },
  "mosquee_goussainville": {
    "latitude": 49.032424,
    "longitude": 2.4509783,
    "name": "Mosquée Essalam - Goussainville",
    "url": "https://mawaqit.net/fr/mosquee-goussainville",
    "label": "Mosquée Essalam - Goussainville",
    "logo": "https://cdn.mawaqit.net/images/backend/mosque/e5dec3e8-f37e-4b02-aa92-a9283a27a45e/mosque/1eee870c-6a20-6fc0-bf7d-0a0c9324ab13.png",
    "site": "http://www.mosquee-goussainville.com",
    "association": "Association Essalam",
    "steamUrl": "UCfGaeHywJAaPdpQMjcwELqA",
    "scrapedAt": "2025-09-21T18:30:19.985502+02:00",
    "parking": true,
    "ablutions": true,
    "ramadanMeal": true,
    "otherInfo": null,
    "womenSpace": true,
    "janazaPrayer": true,
    "aidPrayer": true,
    "adultCourses": true,
    "childrenCourses": true,
    "handicapAccessibility": true,
    "paymentWebsite": "https://www.mosquee-goussainville.com/dons",
    "countryCode": "FR",
    "timezone": "Europe/Paris",
    "image": "https://cdn.mawaqit.net/images/backend/mosque/e5dec3e8-f37e-4b02-aa92-a9283a27a45e/mosque/1efdcd98-99b4-61ec-bc1a-0ac178b258e1.jpg",
    "interiorPicture": "https://cdn.mawaqit.net/images/backend/mosque/e5dec3e8-f37e-4b02-aa92-a9283a27a45e/mosque/1efdcd98-99b4-61ec-bc1a-0ac178b258e1.jpg",
    "exteriorPicture": "https://cdn.mawaqit.net/images/backend/mosque_default_interior_picture.png",
    "calendarUrl": "https://calendar.google.com/calendar/ical/a7b5f55d643de3b945b372a44f2800043978d9c02ec7a156d5e6590a4ed32f8b@group.calendar.google.com/public/basic.ics"
  },
  "masjid_montbeliard": {
    "latitude": 47.4967197,
    "longitude": 6.7976803,
    "name": "مسجد أبي بكر الصديق - Montbéliard",
    "url": "https://mawaqit.net/fr/masjid-montbeliard",
    "label": "مسجد أبي بكر الصديق - Montbéliard",
    "logo": null,
    "site": null,
    "association": "Association de la mosquée de Montbéliard",
    "steamUrl": "",
    "scrapedAt": "2025-09-21T18:34:16.569879+02:00",
    "parking": true,
    "ablutions": true,
    "ramadanMeal": true,
    "otherInfo": null,
    "womenSpace": true,
    "janazaPrayer": true,
    "aidPrayer": true,
    "adultCourses": true,
    "childrenCourses": true,
    "handicapAccessibility": true,
    "paymentWebsite": null,
    "countryCode": "FR",
    "timezone": "Europe/Paris",
    "image": "https://cdn.mawaqit.net/images/backend/mosque/e58c5d89-77a8-4111-b7bf-862a91ea308f/mosque/1eea8d89-f415-6e04-9cbf-066ed47a7584.jpg",
    "interiorPicture": "https://cdn.mawaqit.net/images/backend/mosque/e58c5d89-77a8-4111-b7bf-862a91ea308f/mosque/1eea8d89-f415-6e04-9cbf-066ed47a7584.jpg",
    "exteriorPicture": "https://cdn.mawaqit.net/images/backend/mosque/e58c5d89-77a8-4111-b7bf-862a91ea308f/mosque/1eea8d89-f856-669e-8d39-066ed47a7584.jpg",
    "calendarUrl": "https://calendar.google.com/calendar/ical/580021f21d6141cbbe441b5dfdb263913f8808b1b229250a58d0277eabcfaae0@group.calendar.google.com/public/basic.ics"
  },
  "hamza_garges": {
    "latitude": 48.9778989,
    "longitude": 2.3979211,
    "name": "Masjid Hamza - مسجد حمزة - Garges-lès-gonesse",
    "url": "https://mawaqit.net/fr/hamza-garges",
    "label": "Masjid Hamza - مسجد حمزة - Garges-lès-gonesse",
    "logo": null,
    "site": null,
    "association": "ACCMG",
    "steamUrl": "",
    "scrapedAt": "2025-09-21T18:37:21.946463+02:00",
    "parking": false,
    "ablutions": true,
    "ramadanMeal": true,
    "otherInfo": null,
    "womenSpace": true,
    "janazaPrayer": true,
    "aidPrayer": false,
    "adultCourses": true,
    "childrenCourses": true,
    "handicapAccessibility": true,
    "paymentWebsite": null,
    "countryCode": "FR",
    "timezone": "Europe/Paris",
    "image": "https://cdn.mawaqit.net/images/backend/mosque_default_picture.png",
    "interiorPicture": "https://cdn.mawaqit.net/images/backend/mosque_default_picture.png",
    "exteriorPicture": "https://cdn.mawaqit.net/images/backend/mosque_default_interior_picture.png",
    "calendarUrl": "https://calendar.google.com/calendar/ical/343d85d7abc9d61ae4ae13710311787789b63221417f1d21f86d46d1f17f4746@group.calendar.google.com/public/basic.ics"
  },
  "mosquee_de_libourne": {
    "latitude": 44.9153397,
    "longitude": -0.2223229,
    "name": "Mosquée de Libourne  مسجد ليبورن - LIBOURNE",
    "url": "https://mawaqit.net/fr/mosquee-de-libourne",
    "label": "Mosquée de Libourne  مسجد ليبورن - LIBOURNE",
    "logo": null,
    "site": null,
    "association": "association musulmane de Libourne",
    "steamUrl": "",
    "scrapedAt": "2025-09-21T18:41:22.895678+02:00",
    "parking": true,
    "ablutions": true,
    "ramadanMeal": true,
    "otherInfo": null,
    "womenSpace": true,
    "janazaPrayer": true,
    "aidPrayer": true,
    "adultCourses": false,
    "childrenCourses": false,
    "handicapAccessibility": true,
    "paymentWebsite": null,
    "countryCode": "FR",
    "timezone": "Europe/Paris",
    "image": "https://cdn.mawaqit.net/images/backend/mosque/c73f4fbd-88e3-413c-8b1f-38ec31df2b67/mosque/1eea8d8a-011d-6b9c-8942-066ed47a7584.jpeg",
    "interiorPicture": "https://cdn.mawaqit.net/images/backend/mosque/c73f4fbd-88e3-413c-8b1f-38ec31df2b67/mosque/1eea8d8a-011d-6b9c-8942-066ed47a7584.jpeg",
    "exteriorPicture": "https://cdn.mawaqit.net/images/backend/mosque/c73f4fbd-88e3-413c-8b1f-38ec31df2b67/mosque/1eea8d8a-0696-6a92-a096-066ed47a7584.jpeg",
    "calendarUrl": "https://calendar.google.com/calendar/ical/d0bf31dca10b3c7cad8ce529a4c8841fcabe6a03d4dd52ba153b82ad013e9577@group.calendar.google.com/public/basic.ics"
  },
  "montconseil": {
    "latitude": 48.6006021,
    "longitude": 2.4784612,
    "name": "Mosquée - Montconseil - Corbeil",
    "url": "https://mawaqit.net/fr/montconseil",
    "label": "Mosquée - Montconseil - Corbeil",
    "logo": null,
    "site": "https://mawaqit.net/fr/montconseil",
    "association": "Échange et partage",
    "steamUrl": "",
    "scrapedAt": "2025-09-21T18:45:12.960176+02:00",
    "parking": true,
    "ablutions": true,
    "ramadanMeal": false,
    "otherInfo": null,
    "womenSpace": false,
    "janazaPrayer": false,
    "aidPrayer": true,
    "adultCourses": false,
    "childrenCourses": true,
    "handicapAccessibility": true,
    "paymentWebsite": null,
    "countryCode": "FR",
    "timezone": "Europe/Paris",
    "image": "https://cdn.mawaqit.net/images/backend/mosque_default_picture.png",
    "interiorPicture": "https://cdn.mawaqit.net/images/backend/mosque_default_picture.png",
    "exteriorPicture": "https://cdn.mawaqit.net/images/backend/mosque_default_interior_picture.png",
    "calendarUrl": "https://calendar.google.com/calendar/ical/3863f487ea239364a04b69bbbc5650d7a879941402a999f94cfa1cc672552d76@group.calendar.google.com/public/basic.ics"
  },
  "mosquee_de_rosny_sous": {
    "latitude": 48.8804667,
    "longitude": 2.4817037,
    "name": "Grande Mosquée de Rosny - rosny-sous-bois",
    "url": "https://mawaqit.net/fr/mosquee-de-rosny-sous",
    "label": "Grande Mosquée de Rosny - rosny-sous-bois",
    "logo": "https://cdn.mawaqit.net/images/backend/mosque/d4b9824a-d16c-4d54-af8e-1589b5c85615/mosque/1ef7cfda-0882-64c4-b78c-0ecd6770c589.jpg",
    "site": "http://www.ccrosny.fr",
    "association": "AMR",
    "steamUrl": "",
    "scrapedAt": "2025-09-21T18:48:17.667141+02:00",
    "parking": true,
    "ablutions": true,
    "ramadanMeal": true,
    "otherInfo": "Contactez nous par Telegram à @centreccr",
    "womenSpace": true,
    "janazaPrayer": true,
    "aidPrayer": true,
    "adultCourses": false,
    "childrenCourses": true,
    "handicapAccessibility": true,
    "paymentWebsite": "https://www.paypal.com/donate/?hosted_button_id=ANWSKDHE7YFLA",
    "countryCode": "FR",
    "timezone": "Europe/Paris",
    "image": "https://cdn.mawaqit.net/images/backend/mosque_default_picture.png",
    "interiorPicture": "https://cdn.mawaqit.net/images/backend/mosque_default_picture.png",
    "exteriorPicture": "https://cdn.mawaqit.net/images/backend/mosque_default_interior_picture.png",
    "calendarUrl": "https://calendar.google.com/calendar/ical/1c677cba21372254585b8c721d64515943eb91cf8ff49ca375d0b369f670a02e@group.calendar.google.com/public/basic.ics"
  },
  "mosquee_de_jeumont": {
    "latitude": 50.296548850113,
    "longitude": 4.1018966371055,
    "name": "مسجد الوحدة - Jeumont",
    "url": "https://mawaqit.net/fr/mosquee-de-jeumont",
    "label": "مسجد الوحدة - Jeumont",
    "logo": null,
    "site": null,
    "association": "Association Al Wahda",
    "steamUrl": "",
    "scrapedAt": "2025-09-21T18:51:43.016401+02:00",
    "parking": false,
    "ablutions": true,
    "ramadanMeal": false,
    "otherInfo": null,
    "womenSpace": true,
    "janazaPrayer": true,
    "aidPrayer": true,
    "adultCourses": true,
    "childrenCourses": true,
    "handicapAccessibility": false,
    "paymentWebsite": "https://www.cotizup.com/alwahda-mosquee-jeumont",
    "countryCode": "FR",
    "timezone": "Europe/Paris",
    "image": "https://cdn.mawaqit.net/images/backend/mosque_default_picture.png",
    "interiorPicture": "https://cdn.mawaqit.net/images/backend/mosque_default_picture.png",
    "exteriorPicture": "https://cdn.mawaqit.net/images/backend/mosque_default_interior_picture.png",
    "calendarUrl": "https://calendar.google.com/calendar/ical/164d1692b01e9e982a4616f17af52130f16af5223b4a25f8e1cbe12feeeb71bb@group.calendar.google.com/public/basic.ics"
  },
  "mosquee_de_saint_valerien_saint_valerien": {
    "latitude": 48.1752223,
    "longitude": 3.0927864,
    "name": "Mosquée de Saint-Valérien - Saint-Valérien",
    "url": "https://mawaqit.net/fr/mosquee-de-saint-valerien-saint-valerien",
    "label": "Mosquée de Saint-Valérien - Saint-Valérien",
    "logo": null,
    "site": null,
    "association": "Association Culturelle et Cultuelle de Saint-Valérien",
    "steamUrl": "",
    "scrapedAt": "2025-09-21T18:55:15.333625+02:00",
    "parking": null,
    "ablutions": null,
    "ramadanMeal": null,
    "otherInfo": null,
    "womenSpace": null,
    "janazaPrayer": null,
    "aidPrayer": null,
    "adultCourses": null,
    "childrenCourses": null,
    "handicapAccessibility": null,
    "paymentWebsite": null,
    "countryCode": "FR",
    "timezone": "Europe/Paris",
    "image": "https://cdn.mawaqit.net/images/backend/mosque_default_picture.png",
    "interiorPicture": "https://cdn.mawaqit.net/images/backend/mosque_default_picture.png",
    "exteriorPicture": "https://cdn.mawaqit.net/images/backend/mosque_default_interior_picture.png",
    "calendarUrl": "https://calendar.google.com/calendar/ical/cc7a94102de6d3a6de826c0b032c802f3a8db793baa9c228788da2af7c92529d@group.calendar.google.com/public/basic.ics"
  },
  "mosquee_arrahmane_audincourt": {
    "latitude": 47.4777208,
    "longitude": 6.8401298,
    "name": "مسجد الرحمان-أودانكور - Audincourt",
    "url": "https://mawaqit.net/fr/mosquee-arrahmane-audincourt",
    "label": "مسجد الرحمان-أودانكور - Audincourt",
    "logo": null,
    "site": "https://www.mosquee-audincourt.com/",
    "association": "A.C.M.A",
    "steamUrl": "",
    "scrapedAt": "2025-09-21T18:59:11.759114+02:00",
    "parking": true,
    "ablutions": true,
    "ramadanMeal": true,
    "otherInfo": null,
    "womenSpace": true,
    "janazaPrayer": true,
    "aidPrayer": true,
    "adultCourses": true,
    "childrenCourses": true,
    "handicapAccessibility": true,
    "paymentWebsite": "https://www.helloasso.com/associations/association-cultuelle-des-musulmans-d-audincourt/collectes/projet-extension-mosquee-ar-rahmane-2022",
    "countryCode": "FR",
    "timezone": "Europe/Paris",
    "image": "https://cdn.mawaqit.net/images/backend/mosque/d2f7c04a-9c50-4380-b576-474cf9e91771/mosque/1eea8d8a-117b-6d68-a6ed-066ed47a7584.jpg",
    "interiorPicture": "https://cdn.mawaqit.net/images/backend/mosque/d2f7c04a-9c50-4380-b576-474cf9e91771/mosque/1eea8d8a-117b-6d68-a6ed-066ed47a7584.jpg",
    "exteriorPicture": "https://cdn.mawaqit.net/images/backend/mosque/d2f7c04a-9c50-4380-b576-474cf9e91771/mosque/1eea8d8a-15e4-6cba-90c4-066ed47a7584.jpg",
    "calendarUrl": "https://calendar.google.com/calendar/ical/58b3b4df79409b251c885111bdb4d72a5ef0448172f3b53698356e3b0b27e667@group.calendar.google.com/public/basic.ics"
  },
  "m_grand_charmont": {
    "latitude": 47.5380286,
    "longitude": 6.8233832,
    "name": "مسجد النور - Grand-Charmont",
    "url": "https://mawaqit.net/fr/m-grand-charmont",
    "label": "مسجد النور - Grand-Charmont",
    "logo": null,
    "site": null,
    "association": null,
    "steamUrl": "",
    "scrapedAt": "2025-09-21T19:03:47.147189+02:00",
    "parking": true,
    "ablutions": true,
    "ramadanMeal": false,
    "otherInfo": "IBAN : FR7610278084250002025630129",
    "womenSpace": true,
    "janazaPrayer": true,
    "aidPrayer": true,
    "adultCourses": false,
    "childrenCourses": true,
    "handicapAccessibility": true,
    "paymentWebsite": null,
    "countryCode": "FR",
    "timezone": "Europe/Paris",
    "image": "https://cdn.mawaqit.net/images/backend/mosque/9aae9f50-c645-4b8f-9a4e-10eec5f71e83/mosque/1eea8d8a-1a7a-6bd0-bdca-066ed47a7584.jpg",
    "interiorPicture": "https://cdn.mawaqit.net/images/backend/mosque/9aae9f50-c645-4b8f-9a4e-10eec5f71e83/mosque/1eea8d8a-1a7a-6bd0-bdca-066ed47a7584.jpg",
    "exteriorPicture": "https://cdn.mawaqit.net/images/backend/mosque/9aae9f50-c645-4b8f-9a4e-10eec5f71e83/mosque/1eea8d8a-1eeb-669c-9f47-066ed47a7584.jpg",
    "calendarUrl": "https://calendar.google.com/calendar/ical/dc7f695d64fc4ecdcc043426e1d0d89542f08ac5a62ad9ef3ff049ea45b2990d@group.calendar.google.com/public/basic.ics"
  },
  "msjd_lfjr_joigny_89300_france": {
    "latitude": 47.979943,
    "longitude": 3.4208994,
    "name": "مسجد الفجر - Joigny",
    "url": "https://mawaqit.net/fr/msjd-lfjr-joigny-89300-france",
    "label": "مسجد الفجر - Joigny",
    "logo": null,
    "site": null,
    "association": null,
    "steamUrl": "",
    "scrapedAt": "2025-09-21T19:07:41.844442+02:00",
    "parking": true,
    "ablutions": true,
    "ramadanMeal": true,
    "otherInfo": null,
    "womenSpace": true,
    "janazaPrayer": true,
    "aidPrayer": true,
    "adultCourses": true,
    "childrenCourses": true,
    "handicapAccessibility": true,
    "paymentWebsite": null,
    "countryCode": "FR",
    "timezone": "Europe/Paris",
    "image": "https://cdn.mawaqit.net/images/backend/mosque/443b00b3-eb0f-4cf3-9fc7-faaf2be10599/mosque/1eecf524-7e7d-67e6-a860-0a7eba2dd6b3.jpg",
    "interiorPicture": "https://cdn.mawaqit.net/images/backend/mosque/443b00b3-eb0f-4cf3-9fc7-faaf2be10599/mosque/1eecf524-7e7d-67e6-a860-0a7eba2dd6b3.jpg",
    "exteriorPicture": "https://cdn.mawaqit.net/images/backend/mosque_default_interior_picture.png",
    "calendarUrl": "https://calendar.google.com/calendar/ical/920c81f189c3acee39084e98268b2897b1a496da2c9dcf1274495cf30984e05d@group.calendar.google.com/public/basic.ics"
  },
  "mosquee_ara_rouen": {
    "latitude": 49.4457326,
    "longitude": 1.1189199,
    "name": "Mosquée ARA - Rouen",
    "url": "https://mawaqit.net/fr/mosquee-ara-rouen",
    "label": "Mosquée ARA - Rouen",
    "logo": null,
    "site": null,
    "association": null,
    "steamUrl": "",
    "scrapedAt": "2025-09-21T19:11:19.722322+02:00",
    "parking": null,
    "ablutions": null,
    "ramadanMeal": null,
    "otherInfo": null,
    "womenSpace": null,
    "janazaPrayer": null,
    "aidPrayer": null,
    "adultCourses": null,
    "childrenCourses": null,
    "handicapAccessibility": null,
    "paymentWebsite": null,
    "countryCode": "FR",
    "timezone": "Europe/Paris",
    "image": "https://cdn.mawaqit.net/images/backend/mosque_default_picture.png",
    "interiorPicture": "https://cdn.mawaqit.net/images/backend/mosque_default_picture.png",
    "exteriorPicture": "https://cdn.mawaqit.net/images/backend/mosque_default_interior_picture.png",
    "calendarUrl": "https://calendar.google.com/calendar/ical/059aed84ddf0d141e1fde2a565a26f2bd255f49fd276e0c57534169051f6e7b2@group.calendar.google.com/public/basic.ics"
  },
  "mosquee_yahya_s_e_r": {
    "latitude": 49.3984661,
    "longitude": 1.0756395,
    "name": "Mosquée-Yahya - Saint-Etienne-du-Rouvray",
    "url": "https://mawaqit.net/fr/mosquee-yahya-s-e-r",
    "label": "Mosquée-Yahya - Saint-Etienne-du-Rouvray",
    "logo": null,
    "site": null,
    "association": "ACMS",
    "steamUrl": "",
    "scrapedAt": "2025-09-21T19:15:15.889030+02:00",
    "parking": false,
    "ablutions": true,
    "ramadanMeal": true,
    "otherInfo": null,
    "womenSpace": true,
    "janazaPrayer": true,
    "aidPrayer": true,
    "adultCourses": true,
    "childrenCourses": true,
    "handicapAccessibility": true,
    "paymentWebsite": null,
    "countryCode": "FR",
    "timezone": "UTC",
    "image": "https://cdn.mawaqit.net/images/backend/mosque_default_picture.png",
    "interiorPicture": "https://cdn.mawaqit.net/images/backend/mosque_default_picture.png",
    "exteriorPicture": "https://cdn.mawaqit.net/images/backend/mosque_default_interior_picture.png",
    "calendarUrl": "https://calendar.google.com/calendar/ical/df1215f47d647feb043f683ed36c2701fed8129d14e9b2a4052cbaf0b0095adf@group.calendar.google.com/public/basic.ics"
  },
  "tawba_bussy_saint_georges": {
    "latitude": 48.8384856,
    "longitude": 2.7289757,
    "name": "Mosquée Tawba",
    "url": "https://mawaqit.net/fr/tawba-bussy-saint-georges",
    "label": "Mosquée Tawba",
    "logo": "https://cdn.mawaqit.net/images/backend/mosque/47c8bb95-4f6f-4ca0-b8ae-2d3ffb002f25/mosque/1eea8d8a-23c5-6c12-8151-066ed47a7584.PNG",
    "site": "https://www.mosqueedebussy.fr/",
    "association": "Tawba",
    "steamUrl": "",
    "scrapedAt": "2025-09-21T19:19:19.324778+02:00",
    "parking": true,
    "ablutions": true,
    "ramadanMeal": true,
    "otherInfo": null,
    "womenSpace": true,
    "janazaPrayer": true,
    "aidPrayer": true,
    "adultCourses": true,
    "childrenCourses": true,
    "handicapAccessibility": true,
    "paymentWebsite": "https://mosqueedebussy.fr/donations/gestion-mosquee/",
    "countryCode": "FR",
    "timezone": "Europe/Paris",
    "image": "https://cdn.mawaqit.net/images/backend/mosque_default_picture.png",
    "interiorPicture": "https://cdn.mawaqit.net/images/backend/mosque_default_picture.png",
    "exteriorPicture": "https://cdn.mawaqit.net/images/backend/mosque_default_interior_picture.png",
    "calendarUrl": "https://calendar.google.com/calendar/ical/062965678a56e38a95328f100c054e3025d7c4e8cf51cdbe6ce1aa5417327bbc@group.calendar.google.com/public/basic.ics"
  },
  "mosquee_al_hijra_farebersviller": {
    "latitude": 49.1184421,
    "longitude": 6.8671716,
    "name": "Mosquée AL HIJRA - Farébersviller",
    "url": "https://mawaqit.net/fr/mosquee-al-hijra-farebersviller",
    "label": "Mosquée AL HIJRA - Farébersviller",
    "logo": null,
    "site": null,
    "association": "C.I.M",
    "steamUrl": "",
    "scrapedAt": "2025-09-21T19:23:22.911513+02:00",
    "parking": true,
    "ablutions": true,
    "ramadanMeal": false,
    "otherInfo": null,
    "womenSpace": true,
    "janazaPrayer": true,
    "aidPrayer": true,
    "adultCourses": true,
    "childrenCourses": true,
    "handicapAccessibility": true,
    "paymentWebsite": null,
    "countryCode": "FR",
    "timezone": "Europe/Paris",
    "image": "https://cdn.mawaqit.net/images/backend/mosque/4a735c12-2a5e-4c50-b7a4-e29ccd838466/mosque/1eea8d8a-2875-658c-9732-066ed47a7584.jpg",
    "interiorPicture": "https://cdn.mawaqit.net/images/backend/mosque/4a735c12-2a5e-4c50-b7a4-e29ccd838466/mosque/1eea8d8a-2875-658c-9732-066ed47a7584.jpg",
    "exteriorPicture": "https://cdn.mawaqit.net/images/backend/mosque/4a735c12-2a5e-4c50-b7a4-e29ccd838466/mosque/1eea8d8a-2e42-67c6-ad34-066ed47a7584.jpg",
    "calendarUrl": "https://calendar.google.com/calendar/ical/57c1fa5e510ddaced3f45ecaaed45897f527400a607ea896494e022a2c06b0cf@group.calendar.google.com/public/basic.ics"
  },
  "mosquee_an_nour_cambrai": {
    "latitude": 50.178651,
    "longitude": 3.2322325,
    "name": "Mosquee An Nour - Cambrai",
    "url": "https://mawaqit.net/fr/mosquee-an-nour-cambrai",
    "label": "Mosquee An Nour - Cambrai",
    "logo": null,
    "site": null,
    "association": "Centre culturel du cambraisie",
    "steamUrl": "",
    "scrapedAt": "2025-09-21T19:27:21.375775+02:00",
    "parking": false,
    "ablutions": true,
    "ramadanMeal": true,
    "otherInfo": null,
    "womenSpace": true,
    "janazaPrayer": true,
    "aidPrayer": true,
    "adultCourses": true,
    "childrenCourses": true,
    "handicapAccessibility": true,
    "paymentWebsite": null,
    "countryCode": "FR",
    "timezone": "Europe/Paris",
    "image": "https://cdn.mawaqit.net/images/backend/mosque_default_picture.png",
    "interiorPicture": "https://cdn.mawaqit.net/images/backend/mosque_default_picture.png",
    "exteriorPicture": "https://cdn.mawaqit.net/images/backend/mosque_default_interior_picture.png",
    "calendarUrl": "https://calendar.google.com/calendar/ical/312806a12c6d8137fa378d492e3ad1809efe9d2e6e14a9a57b0cb6480a026431@group.calendar.google.com/public/basic.ics"
  },
  "mosquee_clemence_woippy": {
    "latitude": 49.1475959,
    "longitude": 6.1621081,
    "name": "Mosquée Clémence de Woippy - Woippy",
    "url": "https://mawaqit.net/fr/mosquee-clemence-woippy",
    "label": "Mosquée Clémence de Woippy - Woippy",
    "logo": null,
    "site": "https://www.helloasso.com/associations/association-islamique-clemence",
    "association": "Association Islamique Clémence",
    "steamUrl": "",
    "scrapedAt": "2025-09-21T19:31:13.683528+02:00",
    "parking": true,
    "ablutions": true,
    "ramadanMeal": true,
    "otherInfo": null,
    "womenSpace": true,
    "janazaPrayer": true,
    "aidPrayer": true,
    "adultCourses": true,
    "childrenCourses": true,
    "handicapAccessibility": true,
    "paymentWebsite": "https://www.helloasso.com/associations/association-islamique-clemence",
    "countryCode": "FR",
    "timezone": "Europe/Paris",
    "image": "https://cdn.mawaqit.net/images/backend/mosque/5f10175c-e687-4b87-aef6-d710f8fdc488/mosque/1eea8d8a-3ddb-698a-b726-066ed47a7584.jpg",
    "interiorPicture": "https://cdn.mawaqit.net/images/backend/mosque/5f10175c-e687-4b87-aef6-d710f8fdc488/mosque/1eea8d8a-3ddb-698a-b726-066ed47a7584.jpg",
    "exteriorPicture": "https://cdn.mawaqit.net/images/backend/mosque/5f10175c-e687-4b87-aef6-d710f8fdc488/mosque/1eea8d8a-422f-6a7c-9ced-066ed47a7584.jpeg",
    "calendarUrl": "https://calendar.google.com/calendar/ical/eb31d1f7d81f2ddabca591571a11525ff256b1bcbd517a11d6f3263c76d4e957@group.calendar.google.com/public/basic.ics"
  },
  "msjd_lsn_lynw_goussainville": {
    "latitude": 49.0327111,
    "longitude": 2.4759029,
    "name": "MASJID DES NOUES    مسجد لينو - Goussainville",
    "url": "https://mawaqit.net/fr/msjd-lsn-lynw-goussainville",
    "label": "MASJID DES NOUES    مسجد لينو - Goussainville",
    "logo": "https://cdn.mawaqit.net/images/backend/mosque/8dec5cec-fc66-4fed-83b5-f8dbc7bb7bd8/mosque/1eea8d8a-4744-635a-97ab-066ed47a7584.jpg",
    "site": "https://institutsavoiretetre.fr",
    "association": "Association Paix et Fraternité",
    "steamUrl": "",
    "scrapedAt": "2025-09-21T19:35:09.328890+02:00",
    "parking": false,
    "ablutions": true,
    "ramadanMeal": true,
    "otherInfo": null,
    "womenSpace": false,
    "janazaPrayer": false,
    "aidPrayer": true,
    "adultCourses": true,
    "childrenCourses": true,
    "handicapAccessibility": true,
    "paymentWebsite": null,
    "countryCode": "FR",
    "timezone": "Europe/Paris",
    "image": "https://cdn.mawaqit.net/images/backend/mosque_default_picture.png",
    "interiorPicture": "https://cdn.mawaqit.net/images/backend/mosque_default_picture.png",
    "exteriorPicture": "https://cdn.mawaqit.net/images/backend/mosque_default_interior_picture.png",
    "calendarUrl": "https://calendar.google.com/calendar/ical/41eb078649b8d08fd4f691b2686f52904163efd076662f4d89859701a90a8e75@group.calendar.google.com/public/basic.ics"
  },
  "mosquee_ennour_sartrouville": {
    "latitude": 48.9498302,
    "longitude": 2.1974312,
    "name": "Mosquée Ennour - sartrouville",
    "url": "https://mawaqit.net/fr/mosquee-ennour-sartrouville",
    "label": "Mosquée Ennour - sartrouville",
    "logo": "https://cdn.mawaqit.net/images/backend/mosque/12da7fbb-46c5-443a-a2b8-775383b905fd/mosque/1eeaf347-4a63-666c-8f4b-06acfcd1c88a.png",
    "site": "https://mosquee-sartrouville.fr/",
    "association": "ACMS",
    "steamUrl": "",
    "scrapedAt": "2025-09-21T19:38:16.935680+02:00",
    "parking": true,
    "ablutions": true,
    "ramadanMeal": true,
    "otherInfo": null,
    "womenSpace": true,
    "janazaPrayer": true,
    "aidPrayer": true,
    "adultCourses": true,
    "childrenCourses": true,
    "handicapAccessibility": true,
    "paymentWebsite": "https://www.paypal.com/donate/?hosted_button_id=YA8TCCUEXDX4J",
    "countryCode": "FR",
    "timezone": "Europe/Paris",
    "image": "https://cdn.mawaqit.net/images/backend/mosque_default_picture.png",
    "interiorPicture": "https://cdn.mawaqit.net/images/backend/mosque_default_picture.png",
    "exteriorPicture": "https://cdn.mawaqit.net/images/backend/mosque_default_interior_picture.png",
    "calendarUrl": "https://calendar.google.com/calendar/ical/db344e5e5b36dae9c0fe98a50468bf613994a7110273a48ba9ea71bea84c2cbb@group.calendar.google.com/public/basic.ics"
  },
  "mosquee_erahma_vierzon": {
    "latitude": 47.2242758,
    "longitude": 2.0740127,
    "name": "Mosquée Arrahma - Vierzon",
    "url": "https://mawaqit.net/fr/mosquee-erahma-vierzon",
    "label": "Mosquée Arrahma - Vierzon",
    "logo": null,
    "site": null,
    "association": "Association Cultuelle et Culturelle de Vierzon",
    "steamUrl": "",
    "scrapedAt": "2025-09-26T10:51:11.880393+02:00",
    "parking": false,
    "ablutions": true,
    "ramadanMeal": true,
    "otherInfo": null,
    "womenSpace": true,
    "janazaPrayer": false,
    "aidPrayer": false,
    "adultCourses": false,
    "childrenCourses": true,
    "handicapAccessibility": false,
    "paymentWebsite": null,
    "countryCode": "FR",
    "timezone": "Europe/Paris",
    "image": "https://cdn.mawaqit.net/images/backend/mosque_default_picture.png",
    "interiorPicture": "https://cdn.mawaqit.net/images/backend/mosque_default_picture.png",
    "exteriorPicture": "https://cdn.mawaqit.net/images/backend/mosque_default_interior_picture.png",
    "calendarUrl": "https://calendar.google.com/calendar/ical/1fa60ed6e6cb82512a23c60120240129756063416c51dd9d20dcd67d7f9545fa@group.calendar.google.com/public/basic.ics"
  },
  "mosquee_okba_ibn_nafaa_saint_avold": {
    "latitude": 49.186515,
    "longitude": 6.895295,
    "name": "OKBA IBN NAFAA - SAINT-AVOLD",
    "url": "https://mawaqit.net/fr/mosquee-okba-ibn-nafaa-saint-avold",
    "label": "OKBA IBN NAFAA - SAINT-AVOLD",
    "logo": null,
    "site": null,
    "association": "ASSOCIATION CULTUELLE OKBA-IBN -NAFAA Saint avold",
    "steamUrl": null,
    "scrapedAt": "2025-09-26T10:55:52.617704+02:00",
    "parking": true,
    "ablutions": true,
    "ramadanMeal": true,
    "otherInfo": "Ouverture 20 min avant Fajr, Dohr\r\nFermeture 30 min après Isha\r\nVendredi: Ouverture 1h avant El Jamouaa",
    "womenSpace": true,
    "janazaPrayer": true,
    "aidPrayer": true,
    "adultCourses": false,
    "childrenCourses": true,
    "handicapAccessibility": true,
    "paymentWebsite": null,
    "countryCode": "FR",
    "timezone": "Europe/Paris",
    "image": "https://cdn.mawaqit.net/images/backend/mosque_default_picture.png",
    "interiorPicture": "https://cdn.mawaqit.net/images/backend/mosque_default_picture.png",
    "exteriorPicture": "https://cdn.mawaqit.net/images/backend/mosque_default_interior_picture.png",
    "calendarUrl": "https://calendar.google.com/calendar/ical/c9416ab659b7ef6fc4eca78f974f7d8c6224f91d62846979129742910928d984@group.calendar.google.com/public/basic.ics"
  },
  "jm_lm_lourches": {
    "latitude": 50.3149988,
    "longitude": 3.3656747,
    "name": "جامع الامة - Lourches",
    "url": "https://mawaqit.net/fr/jm-lm-lourches",
    "label": "جامع الامة - Lourches",
    "logo": null,
    "site": "https://fr-fr.facebook.com/people/Asscml-Acml/100009217253625",
    "association": "ACML",
    "steamUrl": "",
    "scrapedAt": "2025-09-26T11:00:36.246727+02:00",
    "parking": true,
    "ablutions": false,
    "ramadanMeal": true,
    "otherInfo": null,
    "womenSpace": false,
    "janazaPrayer": false,
    "aidPrayer": false,
    "adultCourses": false,
    "childrenCourses": false,
    "handicapAccessibility": true,
    "paymentWebsite": null,
    "countryCode": "FR",
    "timezone": "Europe/Paris",
    "image": "https://cdn.mawaqit.net/images/backend/mosque_default_picture.png",
    "interiorPicture": "https://cdn.mawaqit.net/images/backend/mosque_default_picture.png",
    "exteriorPicture": "https://cdn.mawaqit.net/images/backend/mosque_default_interior_picture.png",
    "calendarUrl": "https://calendar.google.com/calendar/ical/7fa0d817a85f100d435e3cf88a542306bb4f7e86dd37e4db2c11f4e8d128195c@group.calendar.google.com/public/basic.ics"
  },
  "mosquee_annour_elbeuf": {
    "latitude": 49.2882642,
    "longitude": 1.0108384,
    "name": "Mosquée Ennour Elbeuf - Elbeuf",
    "url": "https://mawaqit.net/fr/mosquee-annour-elbeuf",
    "label": "Mosquée Ennour Elbeuf - Elbeuf",
    "logo": null,
    "site": "http://mosqueennour.elbeuf.free.fr",
    "association": "Mosquée Ennour",
    "steamUrl": "",
    "scrapedAt": "2025-09-26T11:05:24.387718+02:00",
    "parking": true,
    "ablutions": true,
    "ramadanMeal": false,
    "otherInfo": null,
    "womenSpace": true,
    "janazaPrayer": true,
    "aidPrayer": true,
    "adultCourses": false,
    "childrenCourses": true,
    "handicapAccessibility": true,
    "paymentWebsite": null,
    "countryCode": "FR",
    "timezone": "Europe/Paris",
    "image": "https://cdn.mawaqit.net/images/backend/mosque/dddbf45a-5d32-46ef-9141-7a9b88f7516a/mosque/1eea8d8a-5112-6166-b64a-066ed47a7584.jpg",
    "interiorPicture": "https://cdn.mawaqit.net/images/backend/mosque/dddbf45a-5d32-46ef-9141-7a9b88f7516a/mosque/1eea8d8a-5112-6166-b64a-066ed47a7584.jpg",
    "exteriorPicture": "https://cdn.mawaqit.net/images/backend/mosque_default_interior_picture.png",
    "calendarUrl": "https://calendar.google.com/calendar/ical/d6d7ad98521b63e05823b8a546264527246554a7471ab4912dbdc4bd35c6b2ba@group.calendar.google.com/public/basic.ics"
  },
  "mosquee_acacm_albertville": {
    "latitude": 45.6622517,
    "longitude": 6.3837456,
    "name": "ACACM - Albertville",
    "url": "https://mawaqit.net/fr/mosquee-acacm-albertville",
    "label": "ACACM - Albertville",
    "logo": null,
    "site": null,
    "association": "Association Cultuelle des Albertvilois de Conpfession Musulmane ACACM contactacacm@gmail.com",
    "steamUrl": "",
    "scrapedAt": "2025-09-26T11:10:04.697301+02:00",
    "parking": true,
    "ablutions": true,
    "ramadanMeal": true,
    "otherInfo": null,
    "womenSpace": true,
    "janazaPrayer": true,
    "aidPrayer": true,
    "adultCourses": false,
    "childrenCourses": true,
    "handicapAccessibility": true,
    "paymentWebsite": null,
    "countryCode": "FR",
    "timezone": "Europe/Paris",
    "image": "https://cdn.mawaqit.net/images/backend/mosque/44d34479-67a4-4ebe-8825-1fd438ba5d2c/mosque/1eea8d8a-5674-6c80-929b-066ed47a7584.jpg",
    "interiorPicture": "https://cdn.mawaqit.net/images/backend/mosque/44d34479-67a4-4ebe-8825-1fd438ba5d2c/mosque/1eea8d8a-5674-6c80-929b-066ed47a7584.jpg",
    "exteriorPicture": "https://cdn.mawaqit.net/images/backend/mosque_default_interior_picture.png",
    "calendarUrl": "https://calendar.google.com/calendar/ical/c883e19847c6c5b76314a6fa63e7bb1372a24641fe17e7119f635cc42100b555@group.calendar.google.com/public/basic.ics"
  },
  "mosquee_oumma_de_pau_pau": {
    "latitude": 43.3170733,
    "longitude": -0.3390356,
    "name": "مسجد الأمة - پو - PAU",
    "url": "https://mawaqit.net/fr/mosquee-oumma-de-pau-pau",
    "label": "مسجد الأمة - پو - PAU",
    "logo": null,
    "site": null,
    "association": "Association Mosquée Al Oumma de Pau",
    "steamUrl": "",
    "scrapedAt": "2025-09-26T11:14:46.833145+02:00",
    "parking": true,
    "ablutions": true,
    "ramadanMeal": true,
    "otherInfo": null,
    "womenSpace": true,
    "janazaPrayer": true,
    "aidPrayer": true,
    "adultCourses": true,
    "childrenCourses": true,
    "handicapAccessibility": true,
    "paymentWebsite": null,
    "countryCode": "FR",
    "timezone": "Europe/Paris",
    "image": "https://cdn.mawaqit.net/images/backend/mosque/5218925a-bce1-4ee8-8b11-583da2ca8fd1/mosque/1eea8d8a-5b99-6d64-93c5-066ed47a7584.jpg",
    "interiorPicture": "https://cdn.mawaqit.net/images/backend/mosque/5218925a-bce1-4ee8-8b11-583da2ca8fd1/mosque/1eea8d8a-5b99-6d64-93c5-066ed47a7584.jpg",
    "exteriorPicture": "https://cdn.mawaqit.net/images/backend/mosque/5218925a-bce1-4ee8-8b11-583da2ca8fd1/mosque/1eea8d8a-609e-6c60-bcb0-066ed47a7584.jpg",
    "calendarUrl": "https://calendar.google.com/calendar/ical/01cc7404f5ac8db641edbd6107ebe48ec2c07c84d149edddea0ac97d19844ba9@group.calendar.google.com/public/basic.ics"
  },
  "mosquee_de_la_fraternite_aubervilliers": {
    "latitude": 48.9072266,
    "longitude": 2.3795687,
    "name": "Mosquée La Fraternité - مسجد الأخوة",
    "url": "https://mawaqit.net/fr/mosquee-de-la-fraternite-aubervilliers",
    "label": "Mosquée La Fraternité - مسجد الأخوة",
    "logo": null,
    "site": null,
    "association": "Association La Fraternité",
    "steamUrl": "",
    "scrapedAt": "2025-09-26T11:19:29.386310+02:00",
    "parking": false,
    "ablutions": true,
    "ramadanMeal": true,
    "otherInfo": "Par rapport au couvre-feu la Mosquée ouvre le matin à 6 heure 00 mn",
    "womenSpace": true,
    "janazaPrayer": true,
    "aidPrayer": true,
    "adultCourses": false,
    "childrenCourses": true,
    "handicapAccessibility": true,
    "paymentWebsite": null,
    "countryCode": "FR",
    "timezone": "Europe/Paris",
    "image": "https://cdn.mawaqit.net/images/backend/mosque_default_picture.png",
    "interiorPicture": "https://cdn.mawaqit.net/images/backend/mosque_default_picture.png",
    "exteriorPicture": "https://cdn.mawaqit.net/images/backend/mosque_default_interior_picture.png",
    "calendarUrl": "https://calendar.google.com/calendar/ical/5d89b61034569fe47decb4b74e558fc67115057c6753bddae75d1061f0c696f3@group.calendar.google.com/public/basic.ics"
  },
  "mosquee_fatih_metz": {
    "latitude": 49.1185286,
    "longitude": 6.1890534,
    "name": "Milli Görüş Metz - Fatih Cami - Metz",
    "url": "https://mawaqit.net/fr/mosquee-fatih-metz",
    "label": "Milli Görüş Metz - Fatih Cami - Metz",
    "logo": null,
    "site": "http://www.cimgmetz.fr",
    "association": "CIMG Millî Görüs Metz",
    "steamUrl": "",
    "scrapedAt": "2025-09-26T11:24:30.305989+02:00",
    "parking": true,
    "ablutions": true,
    "ramadanMeal": true,
    "otherInfo": null,
    "womenSpace": true,
    "janazaPrayer": true,
    "aidPrayer": true,
    "adultCourses": true,
    "childrenCourses": true,
    "handicapAccessibility": true,
    "paymentWebsite": null,
    "countryCode": "FR",
    "timezone": "Europe/Paris",
    "image": "https://cdn.mawaqit.net/images/backend/mosque_default_picture.png",
    "interiorPicture": "https://cdn.mawaqit.net/images/backend/mosque_default_picture.png",
    "exteriorPicture": "https://cdn.mawaqit.net/images/backend/mosque_default_interior_picture.png",
    "calendarUrl": "https://calendar.google.com/calendar/ical/de8e44fd6c66b9c0b905dfa13322018c8475235c02b96d368808044482a1714f@group.calendar.google.com/public/basic.ics"
  }
}
